Workbook

Sheet Deckblatt

Sheet Impressum
A4: Impressum
A6: Produktlinie/Reihe: | B6: Tabellen
A8: Produkt-ID: | B8: 729
A10: Titel: | B10: Ausgaben für aktive und passive Leistungen im SGB II (Jahreszahlen)
A12: Region: | B12: Deutschland, West/Ost, Länder und Jobcenter (Gebietsstand Dezember 2024)
A14: Berichtsmonat: | B14: 2024 (Kalenderjahr)
A16: Erstellungsdatum: | B16: 45978
A18: Periodizität: | B18: jährlich
A20: Nächster Veröffentlichungstermin: | B20: 46353
A22: Hinweise: | B22: Für Zwecke der maschinellen Lesbarkeit enthält diese Datei beim Öffnen ausgeblendete Arbeitsblätter mit den unformatierten und nicht gefilterten Grundlagendaten.
A24: Herausgeberin: | B24: Bundesagentur für Arbeit
B25: Statistik
A26: Rückfragen an: | B26: Zentraler Statistik-Service
B27: Regensburger Straße 104
B28: 90478 Nürnberg
A29: E-Mail: | B29: Zentraler-Statistik-Service@arbeitsagentur.de
A30: Hotline: | B30: 0911/179-3632
A33: Internet: | B33: https://statistik.arbeitsagentur.de
A35: Zitierhinweis: | B35: Statistik der Bundesagentur für Arbeit
A38: Nutzungsbedingungen: | B38: © Statistik der Bundesagentur für Arbeit
B39: Die Produkte unterliegen dem Urheberrecht (siehe Impressum).
B40: Daten und Tabellen dürfen uneingeschränkt verwendet werden. Informationen dürfen (auch auszugsweise) gespeichert und mit Quellenangabe weitergegeben, vervielfältigt und verbreitet werden. Die Inhalte dürfen nicht verändert oder verfälscht werden. Eigene Berechnungen sind erlaubt, jedoch als solche kenntlich zu machen. Im Fall einer Veröffentlichung im Internet soll dies mit einer Verlinkung auf die Homepage der Statistik der Bundesagentur für Arbeit erfolgen.

Sheet Inhaltsverzeichnis
F1: Ausgaben im SGB II
A4: Inhaltsverzeichnis
A7: Ausgaben für aktive und passive Leistungen im SGB II (Jahreszahlen)
A8: Deutschland, West/Ost, Länder und Jobcenter (Gebietsstand Dezember 2024)
A9: 2024 (Kalenderjahr)
A11: Tabelle
A13: 1 | B13: Ausgaben für aktive und passive Leistungen im SGB II
A14: 2 | B14: Ausgaben für aktive und passive Leistungen im SGB II - Regionenvergleich
A15: 3 | B15: Eckwerte der Grundsicherung im SGB II
A16: 4 | B16: Zahlungsansprüche im SGB II
A18: Methodische Hinweise
A19: Glossar
A20: Statistik-Infoseite

Sheet 1
I1: Ausgaben im SGB II
A3: Tabelle 1: Ausgaben für aktive und passive Leistungen im SGB II | H3: zurück zum Inhalt
A4: =Steuerung_Eckwerte!C3 -> Deutschland
A5: Jahressumme 2024
A8: Über die Auswahlliste kann die Region ausgesucht werden.
A9: =IF(Steuerung_Eckwerte!E3="H1",Steuerung_Eckwerte!I6,IF(Steuerung_Eckwerte!E3="H2",Steuerung_Eckwerte!I6," ")) -> Mit Ausnahme der Ausgaben für Bildung und Teilhabe wurden die Informationen für Deutschland, Ost- und Westdeutschland sowie die Bundesländer um die unplausiblen bzw. nicht vorhandenen Daten einzelner Jobcenter hochgerechnet. Für unplausible bzw. unvollständige Datenlieferungen im Bereich Eingliederungsleistungen wird bereits auf Jobcenter-Ebene ein Schätzwert gebildet.
A10: =IF(Steuerung_Eckwerte!E3="H1",Steuerung_Eckwerte!I4,IF(Steuerung_Eckwerte!E3="H2",Steuerung_Eckwerte!I5," ")) -> Die Daten für Deutschland insgesamt beinhalten die Buchungen der Jobcenter zuzüglich der Buchungen der Regionaldirektionen, der besonderen Dienststellen und SGB III-Dienststellen (BA) auf Finanzpositionen des SGB II.
D12: 2024 | F12: 2023 | H12: Veränderung der Ausgaben gegenüber dem Vorjahr
D13: Ausgaben | E13: Anteil an Insgesamt in % | F13: Ausgaben | G13: Anteil an Insgesamt in % | H13: absolut | I13: in %
D14: 1 | E14: 2 | F14: 3 | G14: 4 | H14: 5 | I14: 6
A15: =IF(Steuerung_Eckwerte!E3= 1, "Insgesamt 2)", "Insgesamt") -> Insgesamt | C15: Insgesamt (ohne B&T) | D15: =INDEX(Daten!$K$7:$R$430,MATCH(Steuerung_Eckwerte!B$3,Daten!$C$7:$C$430,0),MATCH(C15,Daten!$K$6:$R$6,0)) -> 5.708992e+10 | E15: =IF(ISERROR(D15/D$15),"X",D15/D$15*100) -> 100 | F15: =INDEX(Daten!$S$7:$Z$430,MATCH(Steuerung_Eckwerte!B$3,Daten!$C$7:$C$430,0),MATCH(C15,Daten!$S$6:$Z$6,0)) -> 5.2599183e+10 | G15: =IF(ISERROR(F15/F$15),"X",F15/F$15*100) -> 100 | H15: =INDEX(Daten!$AA$7:$AH$429,MATCH(Steuerung_Eckwerte!B$3,Daten!$C$7:$C$429,0),MATCH(C15,Daten!$AA$6:$AH$6,0)) -> 4.4907374e+09 | I15: =IF(INDEX(Daten!$AI$7:$AP$429,MATCH(Steuerung_Eckwerte!B$3,Daten!$C$7:$C$429,0),MATCH(C15,Daten!$AI$6:$AP$6,0))="X","X",IF(OR(INDEX(Daten!$AI$7:$AP$429,MATCH(Steuerung_Eckwerte!B$3,Daten!$C$7:$C$429,0),MATCH(C15,Daten!$AI$6:$AP$6,0))<(-250),INDEX(Daten!$AI$7:$AP$429,MATCH(Steuerung_Eckwerte!B$3,Daten!$C$7:$C$429,0),MATCH(C15,Daten!$AI$6:$AP$6,0))>250),".X",INDEX(Daten!$AI$7:$AP$429,MATCH(Steuerung_Eckwerte!B$3,Daten!$C$7:$C$429,0),MATCH(C15,Daten!$AI$6:$AP$6,0)))) -> 8.5376563
A16: dav. | B16: Bürgergeld | C16: Bürgergeld (ohne Altfälle) | D16: =INDEX(Daten!$K$7:$R$430,MATCH(Steuerung_Eckwerte!B$3,Daten!$C$7:$C$430,0),MATCH(C16,Daten!$K$6:$R$6,0)) -> 2.2057313e+10 | E16: =IF(ISERROR(D16/D$15),"X",D16/D$15*100) -> 38.63609 | F16: =INDEX(Daten!$S$7:$Z$430,MATCH(Steuerung_Eckwerte!B$3,Daten!$C$7:$C$430,0),MATCH(C16,Daten!$S$6:$Z$6,0)) -> 1.913887e+10 | G16: =IF(ISERROR(F16/F$15),"X",F16/F$15*100) -> 36.38625 | H16: =INDEX(Daten!$AA$7:$AH$429,MATCH(Steuerung_Eckwerte!B$3,Daten!$C$7:$C$429,0),MATCH(C16,Daten!$AA$6:$AH$6,0)) -> 2.9184427e+09 | I16: =IF(INDEX(Daten!$AI$7:$AP$429,MATCH(Steuerung_Eckwerte!B$3,Daten!$C$7:$C$429,0),MATCH(C16,Daten!$AI$6:$AP$6,0))="X","X",IF(OR(INDEX(Daten!$AI$7:$AP$429,MATCH(Steuerung_Eckwerte!B$3,Daten!$C$7:$C$429,0),MATCH(C16,Daten!$AI$6:$AP$6,0))<(-250),INDEX(Daten!$AI$7:$AP$429,MATCH(Steuerung_Eckwerte!B$3,Daten!$C$7:$C$429,0),MATCH(C16,Daten!$AI$6:$AP$6,0))>250),".X",INDEX(Daten!$AI$7:$AP$429,MATCH(Steuerung_Eckwerte!B$3,Daten!$C$7:$C$429,0),MATCH(C16,Daten!$AI$6:$AP$6,0)))) -> 15.248772
B17: Kosten der Unterkunft | C17: Kosten der Unterkunft | D17: =INDEX(Daten!$K$7:$R$430,MATCH(Steuerung_Eckwerte!B$3,Daten!$C$7:$C$430,0),MATCH(C17,Daten!$K$6:$R$6,0)) -> 1.7474337e+10 | E17: =IF(ISERROR(D17/D$15),"X",D17/D$15*100) -> 30.608446 | F17: =INDEX(Daten!$S$7:$Z$430,MATCH(Steuerung_Eckwerte!B$3,Daten!$C$7:$C$430,0),MATCH(C17,Daten!$S$6:$Z$6,0)) -> 1.6520604e+10 | G17: =IF(ISERROR(F17/F$15),"X",F17/F$15*100) -> 31.408481 | H17: =INDEX(Daten!$AA$7:$AH$429,MATCH(Steuerung_Eckwerte!B$3,Daten!$C$7:$C$429,0),MATCH(C17,Daten!$AA$6:$AH$6,0)) -> 9.5373295e+08 | I17: =IF(INDEX(Daten!$AI$7:$AP$429,MATCH(Steuerung_Eckwerte!B$3,Daten!$C$7:$C$429,0),MATCH(C17,Daten!$AI$6:$AP$6,0))="X","X",IF(OR(INDEX(Daten!$AI$7:$AP$429,MATCH(Steuerung_Eckwerte!B$3,Daten!$C$7:$C$429,0),MATCH(C17,Daten!$AI$6:$AP$6,0))<(-250),INDEX(Daten!$AI$7:$AP$429,MATCH(Steuerung_Eckwerte!B$3,Daten!$C$7:$C$429,0),MATCH(C17,Daten!$AI$6:$AP$6,0))>250),".X",INDEX(Daten!$AI$7:$AP$429,MATCH(Steuerung_Eckwerte!B$3,Daten!$C$7:$C$429,0),MATCH(C17,Daten!$AI$6:$AP$6,0)))) -> 5.7729907
B18: Ausgaben für Leistungen zur Sozialversicherung | C18: Ausgaben für Leistungen zur Sozialversicherung | D18: =INDEX(Daten!$K$7:$R$430,MATCH(Steuerung_Eckwerte!B$3,Daten!$C$7:$C$430,0),MATCH(C18,Daten!$K$6:$R$6,0)) -> 7.1652477e+09 | E18: =IF(ISERROR(D18/D$15),"X",D18/D$15*100) -> 12.55081 | F18: =INDEX(Daten!$S$7:$Z$430,MATCH(Steuerung_Eckwerte!B$3,Daten!$C$7:$C$430,0),MATCH(C18,Daten!$S$6:$Z$6,0)) -> 6.686731e+09 | G18: =IF(ISERROR(F18/F$15),"X",F18/F$15*100) -> 12.712614 | H18: =INDEX(Daten!$AA$7:$AH$429,MATCH(Steuerung_Eckwerte!B$3,Daten!$C$7:$C$429,0),MATCH(C18,Daten!$AA$6:$AH$6,0)) -> 4.7851671e+08 | I18: =IF(INDEX(Daten!$AI$7:$AP$429,MATCH(Steuerung_Eckwerte!B$3,Daten!$C$7:$C$429,0),MATCH(C18,Daten!$AI$6:$AP$6,0))="X","X",IF(OR(INDEX(Daten!$AI$7:$AP$429,MATCH(Steuerung_Eckwerte!B$3,Daten!$C$7:$C$429,0),MATCH(C18,Daten!$AI$6:$AP$6,0))<(-250),INDEX(Daten!$AI$7:$AP$429,MATCH(Steuerung_Eckwerte!B$3,Daten!$C$7:$C$429,0),MATCH(C18,Daten!$AI$6:$AP$6,0))>250),".X",INDEX(Daten!$AI$7:$AP$429,MATCH(Steuerung_Eckwerte!B$3,Daten!$C$7:$C$429,0),MATCH(C18,Daten!$AI$6:$AP$6,0)))) -> 7.156213
B19: Eingliederungsleistungen ¹ | C19: Eingliederungsleistungen | D19: =INDEX(Daten!$K$7:$R$430,MATCH(Steuerung_Eckwerte!B$3,Daten!$C$7:$C$430,0),MATCH(C19,Daten!$K$6:$R$6,0)) -> 3.6835652e+09 | E19: =IF(ISERROR(D19/D$15),"X",D19/D$15*100) -> 6.4522164 | F19: =INDEX(Daten!$S$7:$Z$430,MATCH(Steuerung_Eckwerte!B$3,Daten!$C$7:$C$430,0),MATCH(C19,Daten!$S$6:$Z$6,0)) -> 3.8131858e+09 | G19: =IF(ISERROR(F19/F$15),"X",F19/F$15*100) -> 7.2495152 | H19: =INDEX(Daten!$AA$7:$AH$429,MATCH(Steuerung_Eckwerte!B$3,Daten!$C$7:$C$429,0),MATCH(C19,Daten!$AA$6:$AH$6,0)) -> -1.2962056e+08 | I19: =IF(INDEX(Daten!$AI$7:$AP$429,MATCH(Steuerung_Eckwerte!B$3,Daten!$C$7:$C$429,0),MATCH(C19,Daten!$AI$6:$AP$6,0))="X","X",IF(OR(INDEX(Daten!$AI$7:$AP$429,MATCH(Steuerung_Eckwerte!B$3,Daten!$C$7:$C$429,0),MATCH(C19,Daten!$AI$6:$AP$6,0))<(-250),INDEX(Daten!$AI$7:$AP$429,MATCH(Steuerung_Eckwerte!B$3,Daten!$C$7:$C$429,0),MATCH(C19,Daten!$AI$6:$AP$6,0))>250),".X",INDEX(Daten!$AI$7:$AP$429,MATCH(Steuerung_Eckwerte!B$3,Daten!$C$7:$C$429,0),MATCH(C19,Daten!$AI$6:$AP$6,0)))) -> -3.3992721
B20: Verwaltungskosten ² ³ | C20: Verwaltungskosten | D20: =INDEX(Daten!$K$7:$R$430,MATCH(Steuerung_Eckwerte!B$3,Daten!$C$7:$C$430,0),MATCH(C20,Daten!$K$6:$R$6,0)) -> 6.4482995e+09 | E20: =IF(ISERROR(D20/D$15),"X",D20/D$15*100) -> 11.294988 | F20: =INDEX(Daten!$S$7:$Z$430,MATCH(Steuerung_Eckwerte!B$3,Daten!$C$7:$C$430,0),MATCH(C20,Daten!$S$6:$Z$6,0)) -> 6.139999e+09 | G20: =IF(ISERROR(F20/F$15),"X",F20/F$15*100) -> 11.673183 | H20: =INDEX(Daten!$AA$7:$AH$429,MATCH(Steuerung_Eckwerte!B$3,Daten!$C$7:$C$429,0),MATCH(C20,Daten!$AA$6:$AH$6,0)) -> 3.0830053e+08 | I20: =IF(INDEX(Daten!$AI$7:$AP$429,MATCH(Steuerung_Eckwerte!B$3,Daten!$C$7:$C$429,0),MATCH(C20,Daten!$AI$6:$AP$6,0))="X","X",IF(OR(INDEX(Daten!$AI$7:$AP$429,MATCH(Steuerung_Eckwerte!B$3,Daten!$C$7:$C$429,0),MATCH(C20,Daten!$AI$6:$AP$6,0))<(-250),INDEX(Daten!$AI$7:$AP$429,MATCH(Steuerung_Eckwerte!B$3,Daten!$C$7:$C$429,0),MATCH(C20,Daten!$AI$6:$AP$6,0))>250),".X",INDEX(Daten!$AI$7:$AP$429,MATCH(Steuerung_Eckwerte!B$3,Daten!$C$7:$C$429,0),MATCH(C20,Daten!$AI$6:$AP$6,0)))) -> 5.0211822
B21: Abweichend zu erbringende Leistungen | C21: Abweichend zu erbringende Leistungen | D21: =INDEX(Daten!$K$7:$R$430,MATCH(Steuerung_Eckwerte!B$3,Daten!$C$7:$C$430,0),MATCH(C21,Daten!$K$6:$R$6,0)) -> 2.6115767e+08 | E21: =IF(ISERROR(D21/D$15),"X",D21/D$15*100) -> 0.4574497 | F21: =INDEX(Daten!$S$7:$Z$430,MATCH(Steuerung_Eckwerte!B$3,Daten!$C$7:$C$430,0),MATCH(C21,Daten!$S$6:$Z$6,0)) -> 2.9979254e+08 | G21: =IF(ISERROR(F21/F$15),"X",F21/F$15*100) -> 0.56995665 | H21: =INDEX(Daten!$AA$7:$AH$429,MATCH(Steuerung_Eckwerte!B$3,Daten!$C$7:$C$429,0),MATCH(C21,Daten!$AA$6:$AH$6,0)) -> -38634869 | I21: =IF(INDEX(Daten!$AI$7:$AP$429,MATCH(Steuerung_Eckwerte!B$3,Daten!$C$7:$C$429,0),MATCH(C21,Daten!$AI$6:$AP$6,0))="X","X",IF(OR(INDEX(Daten!$AI$7:$AP$429,MATCH(Steuerung_Eckwerte!B$3,Daten!$C$7:$C$429,0),MATCH(C21,Daten!$AI$6:$AP$6,0))<(-250),INDEX(Daten!$AI$7:$AP$429,MATCH(Steuerung_Eckwerte!B$3,Daten!$C$7:$C$429,0),MATCH(C21,Daten!$AI$6:$AP$6,0))>250),".X",INDEX(Daten!$AI$7:$AP$429,MATCH(Steuerung_Eckwerte!B$3,Daten!$C$7:$C$429,0),MATCH(C21,Daten!$AI$6:$AP$6,0)))) -> -12.887202
A22: nachrichtlich: Leistungen für Bildung und Teilhabe ⁴ | C22: Bildung und Teilhabe | D22: =INDEX(Daten!$K$7:$R$430,MATCH(Steuerung_Eckwerte!B$3,Daten!$C$7:$C$430,0),MATCH(C22,Daten!$K$6:$R$6,0)) -> X | E22: X | F22: =INDEX(Daten!$S$7:$Z$430,MATCH(Steuerung_Eckwerte!B$3,Daten!$C$7:$C$430,0),MATCH(C22,Daten!$S$6:$Z$6,0)) -> X | G22: X | H22: =INDEX(Daten!$AA$7:$AH$429,MATCH(Steuerung_Eckwerte!B$3,Daten!$C$7:$C$429,0),MATCH(C22,Daten!$AA$6:$AH$6,0)) -> X | I22: =IF(INDEX(Daten!$AI$7:$AP$429,MATCH(Steuerung_Eckwerte!B$3,Daten!$C$7:$C$429,0),MATCH(C22,Daten!$AI$6:$AP$6,0))="X","X",IF(OR(INDEX(Daten!$AI$7:$AP$429,MATCH(Steuerung_Eckwerte!B$3,Daten!$C$7:$C$429,0),MATCH(C22,Daten!$AI$6:$AP$6,0))<(-250),INDEX(Daten!$AI$7:$AP$429,MATCH(Steuerung_Eckwerte!B$3,Daten!$C$7:$C$429,0),MATCH(C22,Daten!$AI$6:$AP$6,0))>250),".X",INDEX(Daten!$AI$7:$AP$429,MATCH(Steuerung_Eckwerte!B$3,Daten!$C$7:$C$429,0),MATCH(C22,Daten!$AI$6:$AP$6,0)))) -> X
I23: © Statistik der Bundesagentur für Arbeit
A25: =Steuerung_Eckwerte!I10 -> ¹ Umfasst alle Eingliederungsleistungen nach § 16 ff. SGB II (ohne kommunale Eingliederungsleistungen gem. § 16a SGB II), die durch den Bund erstattungsfähig sind. Die Kosten für die Eignungsfeststellung nach § 16 SGB II in Verbindung mit § 32 SGB III können sowohl über das Verwaltungsbudget als auch als Eingliederungsleistung abgerechnet werden.
A26: =Steuerung_Eckwerte!I11 -> ² Die Ausgaben für überörtliche Verwaltungsaufgaben der BA sowie für sonstige überörtlich wahrzunehmende Aufgaben der BA (z.B. SGB II-Statistik) und Sonderbedarfe (z.B. für Organisationsänderungen gemäß § 6a Absatz 7 SGB II und für die Umsetzung der Bundesprogramme) sind nicht enthalten.
A27: =Steuerung_Eckwerte!I12 -> ³ Die Verwaltungsausgaben beinhalten nicht den kommunalen Finanzierungsanteil.
A28: =Steuerung_Eckwerte!I13 -> ⁴ Für die Leistungen für Bildung und Teilhabe nach § 28 SGB II besteht noch keine vollständige Datenübermittlung. Aus diesem Grund werden die Ausgaben für Bildung und Teilhabe nur nachrichtlich für die einzelnen Jobcenter berichtet und fließen daher auch nicht in die Insgesamtsumme ein. Es werden keine Summen für Deutschland, Westdeutschland, Ostdeutschland und für die Bundesländer gebildet. Ein Vorjahresvergleich ist nur eingeschränkt möglich.
A29: =Steuerung_Eckwerte!I14 -> ⁵ Aufgrund von Änderungen in der Regionalzuordnung von Gemeinden zu Jobcentern ist ein Vergleich mit dem Vorjahr nur eingeschränkt möglich.
A32: =Steuerung_Eckwerte!I23 -> ⁶ Trägerfusion: Die Daten beziehen sich auf den Gebietsstand zum Dezember 2022. Die Daten für das Jahr 2021 wurden auf den neuen Gebietsstand umgerechnet.
A34: Grafik 1: Anteile der Ausgabearten an allen Ausgaben im SGB II in %
A35: =Steuerung_Eckwerte!C3 -> Deutschland
A36: =A5 -> Jahressumme 2024

Sheet 2
L1: Ausgaben im SGB II
A3: Tabelle 2: Ausgaben für aktive und passive Leistungen im SGB II - Regionenvergleich | K3: zurück zum Inhalt
A4: Deutschland, West/Ost, Länder und Jobcenter (Gebietsstand Dezember 2024)
A5: Jahressumme 2024
A7: =Steuerung_Eckwerte!I6 -> Mit Ausnahme der Ausgaben für Bildung und Teilhabe wurden die Informationen für Deutschland, Ost- und Westdeutschland sowie die Bundesländer um die unplausiblen bzw. nicht vorhandenen Daten einzelner Jobcenter hochgerechnet. Für unplausible bzw. unvollständige Datenlieferungen im Bereich Eingliederungsleistungen wird bereits auf Jobcenter-Ebene ein Schätzwert gebildet.
A8: =Steuerung_Eckwerte!I4 -> Die Daten für Deutschland insgesamt beinhalten die Buchungen der Jobcenter zuzüglich der Buchungen der Regionaldirektionen, der besonderen Dienststellen und SGB III-Dienststellen (BA) auf Finanzpositionen des SGB II.
A9: =Steuerung_Eckwerte!I5 -> Die Daten für Ost- und Westdeutschland sowie der Bundesländer beinhalten die Buchungen der Jobcenter zuzüglich der Buchungen der SGB III-Dienststellen (BA) auf Finanzpositionen des SGB II. Buchungen der besonderen Dienststellen sowie der Regionaldirektionen sind nicht enthalten.
E11: Insgesamt | F11: dav. (Sp. 1) | L11: nachrichtlich: Leistungen für Bildung und Teilhabe ⁴
A12: Region | B12: Tr Nr | C12: Bundes- land | D12: Ver- gleichs- typ | F12: Bürgergeld | G12: Kosten der Unterkunft | H12: Ausgaben für Leistungen zur Sozialver- sicherung | I12: Einglie- derungs- leistungen ¹ | J12: Verwaltungs- kosten ² ³ | K12: Abweichend zu erbringende Leistungen
E13: 1 | F13: 2 | G13: 3 | H13: 4 | I13: 5 | J13: 6 | K13: 7 | L13: 8
A14: =Daten!C7 -> Deutschland | B14: =Daten!A7 -> D | C14: =Daten!F7 -> D | E14: =INDEX(Daten!$R$7:$R$429,MATCH('2'!B14,Daten!$A$7:$A$429,0)) -> 5.708992e+10 | F14: =INDEX(Daten!$M$7:$M$429,MATCH('2'!B14,Daten!$A$7:$A$429,0)) -> 2.2057313e+10 | G14: =INDEX(Daten!$N$7:$N$429,MATCH('2'!B14,Daten!$A$7:$A$429,0)) -> 1.7474337e+10 | H14: =INDEX(Daten!$P$7:$P$429,MATCH('2'!B14,Daten!$A$7:$A$429,0)) -> 7.1652477e+09 | I14: =INDEX(Daten!$L$7:$L$429,MATCH('2'!B14,Daten!$A$7:$A$429,0)) -> 3.6835652e+09 | J14: =INDEX(Daten!$K$7:$K$429,MATCH('2'!B14,Daten!$A$7:$A$429,0)) -> 6.4482995e+09 | K14: =INDEX(Daten!$O$7:$O$429,MATCH('2'!B14,Daten!$A$7:$A$429,0)) -> 2.6115767e+08 | L14: =INDEX(Daten!$Q$7:$Q$429,MATCH('2'!B14,Daten!$A$7:$A$429,0)) -> X
A15: =Daten!C8 -> Westdeutschland | B15: =Daten!A8 -> W | C15: =Daten!F8 -> W | E15: =INDEX(Daten!$R$7:$R$429,MATCH('2'!B15,Daten!$A$7:$A$429,0)) -> 4.392604e+10 | F15: =INDEX(Daten!$M$7:$M$429,MATCH('2'!B15,Daten!$A$7:$A$429,0)) -> 1.6936316e+10 | G15: =INDEX(Daten!$N$7:$N$429,MATCH('2'!B15,Daten!$A$7:$A$429,0)) -> 1.3642556e+10 | H15: =INDEX(Daten!$P$7:$P$429,MATCH('2'!B15,Daten!$A$7:$A$429,0)) -> 5.5042137e+09 | I15: =INDEX(Daten!$L$7:$L$429,MATCH('2'!B15,Daten!$A$7:$A$429,0)) -> 2.7969838e+09 | J15: =INDEX(Daten!$K$7:$K$429,MATCH('2'!B15,Daten!$A$7:$A$429,0)) -> 4.8514269e+09 | K15: =INDEX(Daten!$O$7:$O$429,MATCH('2'!B15,Daten!$A$7:$A$429,0)) -> 1.9454309e+08 | L15: =INDEX(Daten!$Q$7:$Q$429,MATCH('2'!B15,Daten!$A$7:$A$429,0)) -> X
A16: =Daten!C9 -> Ostdeutschland | B16: =Daten!A9 -> O | C16: =Daten!F9 -> O | E16: =INDEX(Daten!$R$7:$R$429,MATCH('2'!B16,Daten!$A$7:$A$429,0)) -> 1.3163631e+10 | F16: =INDEX(Daten!$M$7:$M$429,MATCH('2'!B16,Daten!$A$7:$A$429,0)) -> 5.1209971e+09 | G16: =INDEX(Daten!$N$7:$N$429,MATCH('2'!B16,Daten!$A$7:$A$429,0)) -> 3.8317814e+09 | H16: =INDEX(Daten!$P$7:$P$429,MATCH('2'!B16,Daten!$A$7:$A$429,0)) -> 1.6607843e+09 | I16: =INDEX(Daten!$L$7:$L$429,MATCH('2'!B16,Daten!$A$7:$A$429,0)) -> 8.8658143e+08 | J16: =INDEX(Daten!$K$7:$K$429,MATCH('2'!B16,Daten!$A$7:$A$429,0)) -> 1.5968726e+09 | K16: =INDEX(Daten!$O$7:$O$429,MATCH('2'!B16,Daten!$A$7:$A$429,0)) -> 66614581 | L16: =INDEX(Daten!$Q$7:$Q$429,MATCH('2'!B16,Daten!$A$7:$A$429,0)) -> X
A17: =Daten!C10 -> Schleswig-Holstein | B17: =Daten!A10 -> 01 | C17: =Daten!F10 -> 01 | E17: =INDEX(Daten!$R$7:$R$429,MATCH('2'!B17,Daten!$A$7:$A$429,0)) -> 1.992957e+09 | F17: =INDEX(Daten!$M$7:$M$429,MATCH('2'!B17,Daten!$A$7:$A$429,0)) -> 7.5816658e+08 | G17: =INDEX(Daten!$N$7:$N$429,MATCH('2'!B17,Daten!$A$7:$A$429,0)) -> 6.1669803e+08 | H17: =INDEX(Daten!$P$7:$P$429,MATCH('2'!B17,Daten!$A$7:$A$429,0)) -> 2.5403216e+08 | I17: =INDEX(Daten!$L$7:$L$429,MATCH('2'!B17,Daten!$A$7:$A$429,0)) -> 1.2317052e+08 | J17: =INDEX(Daten!$K$7:$K$429,MATCH('2'!B17,Daten!$A$7:$A$429,0)) -> 2.3318588e+08 | K17: =INDEX(Daten!$O$7:$O$429,MATCH('2'!B17,Daten!$A$7:$A$429,0)) -> 7703793.3 | L17: =INDEX(Daten!$Q$7:$Q$429,MATCH('2'!B17,Daten!$A$7:$A$429,0)) -> X
A18: =Daten!C11 -> Hamburg | B18: =Daten!A11 -> 02 | C18: =Daten!F11 -> 02 | E18: =INDEX(Daten!$R$7:$R$429,MATCH('2'!B18,Daten!$A$7:$A$429,0)) -> 2.2194536e+09 | F18: =INDEX(Daten!$M$7:$M$429,MATCH('2'!B18,Daten!$A$7:$A$429,0)) -> 7.6029079e+08 | G18: =INDEX(Daten!$N$7:$N$429,MATCH('2'!B18,Daten!$A$7:$A$429,0)) -> 8.5394905e+08 | H18: =INDEX(Daten!$P$7:$P$429,MATCH('2'!B18,Daten!$A$7:$A$429,0)) -> 2.4685997e+08 | I18: =INDEX(Daten!$L$7:$L$429,MATCH('2'!B18,Daten!$A$7:$A$429,0)) -> 1.5194415e+08 | J18: =INDEX(Daten!$K$7:$K$429,MATCH('2'!B18,Daten!$A$7:$A$429,0)) -> 1.9823893e+08 | K18: =INDEX(Daten!$O$7:$O$429,MATCH('2'!B18,Daten!$A$7:$A$429,0)) -> 8170745.2 | L18: =INDEX(Daten!$Q$7:$Q$429,MATCH('2'!B18,Daten!$A$7:$A$429,0)) -> X
A19: =Daten!C12 -> Niedersachsen | B19: =Daten!A12 -> 03 | C19: =Daten!F12 -> 03 | E19: =INDEX(Daten!$R$7:$R$429,MATCH('2'!B19,Daten!$A$7:$A$429,0)) -> 5.4197362e+09 | F19: =INDEX(Daten!$M$7:$M$429,MATCH('2'!B19,Daten!$A$7:$A$429,0)) -> 2.103907e+09 | G19: =INDEX(Daten!$N$7:$N$429,MATCH('2'!B19,Daten!$A$7:$A$429,0)) -> 1.6311256e+09 | H19: =INDEX(Daten!$P$7:$P$429,MATCH('2'!B19,Daten!$A$7:$A$429,0)) -> 6.895851e+08 | I19: =INDEX(Daten!$L$7:$L$429,MATCH('2'!B19,Daten!$A$7:$A$429,0)) -> 3.3759138e+08 | J19: =INDEX(Daten!$K$7:$K$429,MATCH('2'!B19,Daten!$A$7:$A$429,0)) -> 6.3524431e+08 | K19: =INDEX(Daten!$O$7:$O$429,MATCH('2'!B19,Daten!$A$7:$A$429,0)) -> 22282760 | L19: =INDEX(Daten!$Q$7:$Q$429,MATCH('2'!B19,Daten!$A$7:$A$429,0)) -> X
A20: =Daten!C13 -> Bremen | B20: =Daten!A13 -> 04 | C20: =Daten!F13 -> 04 | E20: =INDEX(Daten!$R$7:$R$429,MATCH('2'!B20,Daten!$A$7:$A$429,0)) -> 1.0017576e+09 | F20: =INDEX(Daten!$M$7:$M$429,MATCH('2'!B20,Daten!$A$7:$A$429,0)) -> 3.8674713e+08 | G20: =INDEX(Daten!$N$7:$N$429,MATCH('2'!B20,Daten!$A$7:$A$429,0)) -> 3.0300354e+08 | H20: =INDEX(Daten!$P$7:$P$429,MATCH('2'!B20,Daten!$A$7:$A$429,0)) -> 1.2249299e+08 | I20: =INDEX(Daten!$L$7:$L$429,MATCH('2'!B20,Daten!$A$7:$A$429,0)) -> 80920806 | J20: =INDEX(Daten!$K$7:$K$429,MATCH('2'!B20,Daten!$A$7:$A$429,0)) -> 1.032326e+08 | K20: =INDEX(Daten!$O$7:$O$429,MATCH('2'!B20,Daten!$A$7:$A$429,0)) -> 5360530.6 | L20: =INDEX(Daten!$Q$7:$Q$429,MATCH('2'!B20,Daten!$A$7:$A$429,0)) -> X
A21: =Daten!C14 -> Nordrhein-Westfalen | B21: =Daten!A14 -> 05 | C21: =Daten!F14 -> 05 | E21: =INDEX(Daten!$R$7:$R$429,MATCH('2'!B21,Daten!$A$7:$A$429,0)) -> 1.6301383e+10 | F21: =INDEX(Daten!$M$7:$M$429,MATCH('2'!B21,Daten!$A$7:$A$429,0)) -> 6.38929e+09 | G21: =INDEX(Daten!$N$7:$N$429,MATCH('2'!B21,Daten!$A$7:$A$429,0)) -> 4.8839967e+09 | H21: =INDEX(Daten!$P$7:$P$429,MATCH('2'!B21,Daten!$A$7:$A$429,0)) -> 2.0318916e+09 | I21: =INDEX(Daten!$L$7:$L$429,MATCH('2'!B21,Daten!$A$7:$A$429,0)) -> 1.1727391e+09 | J21: =INDEX(Daten!$K$7:$K$429,MATCH('2'!B21,Daten!$A$7:$A$429,0)) -> 1.7527622e+09 | K21: =INDEX(Daten!$O$7:$O$429,MATCH('2'!B21,Daten!$A$7:$A$429,0)) -> 70703407 | L21: =INDEX(Daten!$Q$7:$Q$429,MATCH('2'!B21,Daten!$A$7:$A$429,0)) -> X
A22: =Daten!C15 -> Hessen | B22: =Daten!A15 -> 06 | C22: =Daten!F15 -> 06 | E22: =INDEX(Daten!$R$7:$R$429,MATCH('2'!B22,Daten!$A$7:$A$429,0)) -> 4.2758934e+09 | F22: =INDEX(Daten!$M$7:$M$429,MATCH('2'!B22,Daten!$A$7:$A$429,0)) -> 1.6029478e+09 | G22: =INDEX(Daten!$N$7:$N$429,MATCH('2'!B22,Daten!$A$7:$A$429,0)) -> 1.419614e+09 | H22: =INDEX(Daten!$P$7:$P$429,MATCH('2'!B22,Daten!$A$7:$A$429,0)) -> 5.2769935e+08 | I22: =INDEX(Daten!$L$7:$L$429,MATCH('2'!B22,Daten!$A$7:$A$429,0)) -> 2.2169137e+08 | J22: =INDEX(Daten!$K$7:$K$429,MATCH('2'!B22,Daten!$A$7:$A$429,0)) -> 4.8154224e+08 | K22: =INDEX(Daten!$O$7:$O$429,MATCH('2'!B22,Daten!$A$7:$A$429,0)) -> 22398623 | L22: =INDEX(Daten!$Q$7:$Q$429,MATCH('2'!B22,Daten!$A$7:$A$429,0)) -> X
A23: =Daten!C16 -> Rheinland-Pfalz | B23: =Daten!A16 -> 07 | C23: =Daten!F16 -> 07 | E23: =INDEX(Daten!$R$7:$R$429,MATCH('2'!B23,Daten!$A$7:$A$429,0)) -> 2.214668e+09 | F23: =INDEX(Daten!$M$7:$M$429,MATCH('2'!B23,Daten!$A$7:$A$429,0)) -> 8.8660923e+08 | G23: =INDEX(Daten!$N$7:$N$429,MATCH('2'!B23,Daten!$A$7:$A$429,0)) -> 6.4972071e+08 | H23: =INDEX(Daten!$P$7:$P$429,MATCH('2'!B23,Daten!$A$7:$A$429,0)) -> 2.9025144e+08 | I23: =INDEX(Daten!$L$7:$L$429,MATCH('2'!B23,Daten!$A$7:$A$429,0)) -> 1.2340632e+08 | J23: =INDEX(Daten!$K$7:$K$429,MATCH('2'!B23,Daten!$A$7:$A$429,0)) -> 2.5658537e+08 | K23: =INDEX(Daten!$O$7:$O$429,MATCH('2'!B23,Daten!$A$7:$A$429,0)) -> 8094916.3 | L23: =INDEX(Daten!$Q$7:$Q$429,MATCH('2'!B23,Daten!$A$7:$A$429,0)) -> X
A24: =Daten!C17 -> Baden-Württemberg | B24: =Daten!A17 -> 08 | C24: =Daten!F17 -> 08 | E24: =INDEX(Daten!$R$7:$R$429,MATCH('2'!B24,Daten!$A$7:$A$429,0)) -> 5.0835535e+09 | F24: =INDEX(Daten!$M$7:$M$429,MATCH('2'!B24,Daten!$A$7:$A$429,0)) -> 1.9391078e+09 | G24: =INDEX(Daten!$N$7:$N$429,MATCH('2'!B24,Daten!$A$7:$A$429,0)) -> 1.6447576e+09 | H24: =INDEX(Daten!$P$7:$P$429,MATCH('2'!B24,Daten!$A$7:$A$429,0)) -> 6.3990268e+08 | I24: =INDEX(Daten!$L$7:$L$429,MATCH('2'!B24,Daten!$A$7:$A$429,0)) -> 2.9385662e+08 | J24: =INDEX(Daten!$K$7:$K$429,MATCH('2'!B24,Daten!$A$7:$A$429,0)) -> 5.4408124e+08 | K24: =INDEX(Daten!$O$7:$O$429,MATCH('2'!B24,Daten!$A$7:$A$429,0)) -> 21847516 | L24: =INDEX(Daten!$Q$7:$Q$429,MATCH('2'!B24,Daten!$A$7:$A$429,0)) -> X
A25: =Daten!C18 -> Bayern | B25: =Daten!A18 -> 09 | C25: =Daten!F18 -> 09 | E25: =INDEX(Daten!$R$7:$R$429,MATCH('2'!B25,Daten!$A$7:$A$429,0)) -> 4.574464e+09 | F25: =INDEX(Daten!$M$7:$M$429,MATCH('2'!B25,Daten!$A$7:$A$429,0)) -> 1.7753399e+09 | G25: =INDEX(Daten!$N$7:$N$429,MATCH('2'!B25,Daten!$A$7:$A$429,0)) -> 1.3935529e+09 | H25: =INDEX(Daten!$P$7:$P$429,MATCH('2'!B25,Daten!$A$7:$A$429,0)) -> 5.9508966e+08 | I25: =INDEX(Daten!$L$7:$L$429,MATCH('2'!B25,Daten!$A$7:$A$429,0)) -> 2.341262e+08 | J25: =INDEX(Daten!$K$7:$K$429,MATCH('2'!B25,Daten!$A$7:$A$429,0)) -> 5.5203433e+08 | K25: =INDEX(Daten!$O$7:$O$429,MATCH('2'!B25,Daten!$A$7:$A$429,0)) -> 24320913 | L25: =INDEX(Daten!$Q$7:$Q$429,MATCH('2'!B25,Daten!$A$7:$A$429,0)) -> X
... A32: =Daten!C25 -> Thüringen | B32: =Daten!A25 -> 16 | C32: =Daten!F25 -> 16 | E32: =INDEX(Daten!$R$7:$R$429,MATCH('2'!B32,Daten!$A$7:$A$429,0)) -> 1.1744005e+09 | F32: =INDEX(Daten!$M$7:$M$429,MATCH('2'!B32,Daten!$A$7:$A$429,0)) -> 4.8771278e+08 | G32: =INDEX(Daten!$N$7:$N$429,MATCH('2'!B32,Daten!$A$7:$A$429,0)) -> 2.957966e+08 | H32: =INDEX(Daten!$P$7:$P$429,MATCH('2'!B32,Daten!$A$7:$A$429,0)) -> 1.5744493e+08 | I32: =INDEX(Daten!$L$7:$L$429,MATCH('2'!B32,Daten!$A$7:$A$429,0)) -> 64205636 | J32: =INDEX(Daten!$K$7:$K$429,MATCH('2'!B32,Daten!$A$7:$A$429,0)) -> 1.6236192e+08 | K32: =INDEX(Daten!$O$7:$O$429,MATCH('2'!B32,Daten!$A$7:$A$429,0)) -> 6878601.8 | L32: =INDEX(Daten!$Q$7:$Q$429,MATCH('2'!B32,Daten!$A$7:$A$429,0)) -> X
A33: =Daten!C26 -> JC Vorpommern-Greifswald | B33: =Daten!A26 -> 03002 | C33: =Daten!F26 -> 13 | D33: =Daten!E26 -> IIId | E33: =INDEX(Daten!$R$7:$R$429,MATCH('2'!B33,Daten!$A$7:$A$429,0)) -> 1.8160685e+08 | F33: =INDEX(Daten!$M$7:$M$429,MATCH('2'!B33,Daten!$A$7:$A$429,0)) -> 73434908 | G33: =INDEX(Daten!$N$7:$N$429,MATCH('2'!B33,Daten!$A$7:$A$429,0)) -> 45391276 | H33: =INDEX(Daten!$P$7:$P$429,MATCH('2'!B33,Daten!$A$7:$A$429,0)) -> 23870983 | I33: =INDEX(Daten!$L$7:$L$429,MATCH('2'!B33,Daten!$A$7:$A$429,0)) -> 12585733 | J33: =INDEX(Daten!$K$7:$K$429,MATCH('2'!B33,Daten!$A$7:$A$429,0)) -> 25300148 | K33: =INDEX(Daten!$O$7:$O$429,MATCH('2'!B33,Daten!$A$7:$A$429,0)) -> 1023801.2 | L33: =INDEX(Daten!$Q$7:$Q$429,MATCH('2'!B33,Daten!$A$7:$A$429,0)) -> 2276910.6
A34: =Daten!C27 -> JC Mecklenburgische Seenplatte Süd | B34: =Daten!A27 -> 03102 | C34: =Daten!F27 -> 13 | D34: =Daten!E27 -> IIId | E34: =INDEX(Daten!$R$7:$R$429,MATCH('2'!B34,Daten!$A$7:$A$429,0)) -> 1.2304391e+08 | F34: =INDEX(Daten!$M$7:$M$429,MATCH('2'!B34,Daten!$A$7:$A$429,0)) -> 50412561 | G34: =INDEX(Daten!$N$7:$N$429,MATCH('2'!B34,Daten!$A$7:$A$429,0)) -> 31117423 | H34: =INDEX(Daten!$P$7:$P$429,MATCH('2'!B34,Daten!$A$7:$A$429,0)) -> 16241827 | I34: =INDEX(Daten!$L$7:$L$429,MATCH('2'!B34,Daten!$A$7:$A$429,0)) -> 7073905.6 | J34: =INDEX(Daten!$K$7:$K$429,MATCH('2'!B34,Daten!$A$7:$A$429,0)) -> 17339875 | K34: =INDEX(Daten!$O$7:$O$429,MATCH('2'!B34,Daten!$A$7:$A$429,0)) -> 858317.28 | L34: =INDEX(Daten!$Q$7:$Q$429,MATCH('2'!B34,Daten!$A$7:$A$429,0)) -> 1775195.9
A35: =Daten!C28 -> JC Mecklenburgische Seenplatte Nord | B35: =Daten!A28 -> 03122 | C35: =Daten!F28 -> 13 | D35: =Daten!E28 -> IIId | E35: =INDEX(Daten!$R$7:$R$429,MATCH('2'!B35,Daten!$A$7:$A$429,0)) -> 79598044 | F35: =INDEX(Daten!$M$7:$M$429,MATCH('2'!B35,Daten!$A$7:$A$429,0)) -> 32101052 | G35: =INDEX(Daten!$N$7:$N$429,MATCH('2'!B35,Daten!$A$7:$A$429,0)) -> 19767628 | H35: =INDEX(Daten!$P$7:$P$429,MATCH('2'!B35,Daten!$A$7:$A$429,0)) -> 10390224 | I35: =INDEX(Daten!$L$7:$L$429,MATCH('2'!B35,Daten!$A$7:$A$429,0)) -> 4007727 | J35: =INDEX(Daten!$K$7:$K$429,MATCH('2'!B35,Daten!$A$7:$A$429,0)) -> 12866847 | K35: =INDEX(Daten!$O$7:$O$429,MATCH('2'!B35,Daten!$A$7:$A$429,0)) -> 464567.08 | L35: =INDEX(Daten!$Q$7:$Q$429,MATCH('2'!B35,Daten!$A$7:$A$429,0)) -> 932499.98
A36: =Daten!C29 -> JC Rostock, Hansestadt | B36: =Daten!A29 -> 03202 | C36: =Daten!F29 -> 13 | D36: =Daten!E29 -> IIIe | E36: =INDEX(Daten!$R$7:$R$429,MATCH('2'!B36,Daten!$A$7:$A$429,0)) -> 1.6461302e+08 | F36: =INDEX(Daten!$M$7:$M$429,MATCH('2'!B36,Daten!$A$7:$A$429,0)) -> 64311827 | G36: =INDEX(Daten!$N$7:$N$429,MATCH('2'!B36,Daten!$A$7:$A$429,0)) -> 45230145 | H36: =INDEX(Daten!$P$7:$P$429,MATCH('2'!B36,Daten!$A$7:$A$429,0)) -> 21574233 | I36: =INDEX(Daten!$L$7:$L$429,MATCH('2'!B36,Daten!$A$7:$A$429,0)) -> 9931609.6 | J36: =INDEX(Daten!$K$7:$K$429,MATCH('2'!B36,Daten!$A$7:$A$429,0)) -> 22567061 | K36: =INDEX(Daten!$O$7:$O$429,MATCH('2'!B36,Daten!$A$7:$A$429,0)) -> 998142.2 | L36: =INDEX(Daten!$Q$7:$Q$429,MATCH('2'!B36,Daten!$A$7:$A$429,0)) -> 768130.98
A37: =Daten!C30 -> JC Landkreis Rostock | B37: =Daten!A30 -> 03208 | C37: =Daten!F30 -> 13 | D37: =Daten!E30 -> IIIa | E37: =INDEX(Daten!$R$7:$R$429,MATCH('2'!B37,Daten!$A$7:$A$429,0)) -> 1.18883e+08 | F37: =INDEX(Daten!$M$7:$M$429,MATCH('2'!B37,Daten!$A$7:$A$429,0)) -> 48224427 | G37: =INDEX(Daten!$N$7:$N$429,MATCH('2'!B37,Daten!$A$7:$A$429,0)) -> 31607849 | H37: =INDEX(Daten!$P$7:$P$429,MATCH('2'!B37,Daten!$A$7:$A$429,0)) -> 15334952 | I37: =INDEX(Daten!$L$7:$L$429,MATCH('2'!B37,Daten!$A$7:$A$429,0)) -> 8058731.3 | J37: =INDEX(Daten!$K$7:$K$429,MATCH('2'!B37,Daten!$A$7:$A$429,0)) -> 15117537 | K37: =INDEX(Daten!$O$7:$O$429,MATCH('2'!B37,Daten!$A$7:$A$429,0)) -> 539498.75 | L37: =INDEX(Daten!$Q$7:$Q$429,MATCH('2'!B37,Daten!$A$7:$A$429,0)) -> 1581754
A38: =Daten!C31 -> JC Schwerin, Landeshauptstadt | B38: =Daten!A31 -> 03302 | C38: =Daten!F31 -> 13 | D38: =Daten!E31 -> IIIe | E38: =INDEX(Daten!$R$7:$R$429,MATCH('2'!B38,Daten!$A$7:$A$429,0)) -> 1.0992199e+08 | F38: =INDEX(Daten!$M$7:$M$429,MATCH('2'!B38,Daten!$A$7:$A$429,0)) -> 44877132 | G38: =INDEX(Daten!$N$7:$N$429,MATCH('2'!B38,Daten!$A$7:$A$429,0)) -> 28679218 | H38: =INDEX(Daten!$P$7:$P$429,MATCH('2'!B38,Daten!$A$7:$A$429,0)) -> 14314467 | I38: =INDEX(Daten!$L$7:$L$429,MATCH('2'!B38,Daten!$A$7:$A$429,0)) -> 7746878.9 | J38: =INDEX(Daten!$K$7:$K$429,MATCH('2'!B38,Daten!$A$7:$A$429,0)) -> 13145604 | K38: =INDEX(Daten!$O$7:$O$429,MATCH('2'!B38,Daten!$A$7:$A$429,0)) -> 1158691.5 | L38: =INDEX(Daten!$Q$7:$Q$429,MATCH('2'!B38,Daten!$A$7:$A$429,0)) -> 1989494.8
A39: =Daten!C32 -> JC Nordwestmecklenburg | B39: =Daten!A32 -> 03304 | C39: =Daten!F32 -> 13 | D39: =Daten!E32 -> IIIa | E39: =INDEX(Daten!$R$7:$R$429,MATCH('2'!B39,Daten!$A$7:$A$429,0)) -> 89966541 | F39: =INDEX(Daten!$M$7:$M$429,MATCH('2'!B39,Daten!$A$7:$A$429,0)) -> 36695688 | G39: =INDEX(Daten!$N$7:$N$429,MATCH('2'!B39,Daten!$A$7:$A$429,0)) -> 22717096 | H39: =INDEX(Daten!$P$7:$P$429,MATCH('2'!B39,Daten!$A$7:$A$429,0)) -> 11957198 | I39: =INDEX(Daten!$L$7:$L$429,MATCH('2'!B39,Daten!$A$7:$A$429,0)) -> 5892383.4 | J39: =INDEX(Daten!$K$7:$K$429,MATCH('2'!B39,Daten!$A$7:$A$429,0)) -> 12398500 | K39: =INDEX(Daten!$O$7:$O$429,MATCH('2'!B39,Daten!$A$7:$A$429,0)) -> 305675.52 | L39: =INDEX(Daten!$Q$7:$Q$429,MATCH('2'!B39,Daten!$A$7:$A$429,0)) -> 407111.45
A40: =Daten!C33 -> JC Ludwigslust-Parchim | B40: =Daten!A33 -> 03324 | C40: =Daten!F33 -> 13 | D40: =Daten!E33 -> IIId | E40: =INDEX(Daten!$R$7:$R$429,MATCH('2'!B40,Daten!$A$7:$A$429,0)) -> 1.099409e+08 | F40: =INDEX(Daten!$M$7:$M$429,MATCH('2'!B40,Daten!$A$7:$A$429,0)) -> 46079781 | G40: =INDEX(Daten!$N$7:$N$429,MATCH('2'!B40,Daten!$A$7:$A$429,0)) -> 26435416 | H40: =INDEX(Daten!$P$7:$P$429,MATCH('2'!B40,Daten!$A$7:$A$429,0)) -> 14356149 | I40: =INDEX(Daten!$L$7:$L$429,MATCH('2'!B40,Daten!$A$7:$A$429,0)) -> 7394498.3 | J40: =INDEX(Daten!$K$7:$K$429,MATCH('2'!B40,Daten!$A$7:$A$429,0)) -> 14990419 | K40: =INDEX(Daten!$O$7:$O$429,MATCH('2'!B40,Daten!$A$7:$A$429,0)) -> 684633.98 | L40: =INDEX(Daten!$Q$7:$Q$429,MATCH('2'!B40,Daten!$A$7:$A$429,0)) -> 1553636.5
A41: =Daten!C34 -> JC Vorpommern-Rügen | B41: =Daten!A34 -> 03444 | C41: =Daten!F34 -> 13 | D41: =Daten!E34 -> IIId | E41: =INDEX(Daten!$R$7:$R$429,MATCH('2'!B41,Daten!$A$7:$A$429,0)) -> . | F41: =INDEX(Daten!$M$7:$M$429,MATCH('2'!B41,Daten!$A$7:$A$429,0)) -> 65200239 | G41: =INDEX(Daten!$N$7:$N$429,MATCH('2'!B41,Daten!$A$7:$A$429,0)) -> 43275418 | H41: =INDEX(Daten!$P$7:$P$429,MATCH('2'!B41,Daten!$A$7:$A$429,0)) -> 21515054 | I41: =INDEX(Daten!$L$7:$L$429,MATCH('2'!B41,Daten!$A$7:$A$429,0)) -> 11464732 | J41: =INDEX(Daten!$K$7:$K$429,MATCH('2'!B41,Daten!$A$7:$A$429,0)) -> . | K41: =INDEX(Daten!$O$7:$O$429,MATCH('2'!B41,Daten!$A$7:$A$429,0)) -> 1080477 | L41: =INDEX(Daten!$Q$7:$Q$429,MATCH('2'!B41,Daten!$A$7:$A$429,0)) -> 453355
A42: =Daten!C35 -> JC Cottbus, Stadt | B42: =Daten!A35 -> 03502 | C42: =Daten!F35 -> 12 | D42: =Daten!E35 -> IIIe | E42: =INDEX(Daten!$R$7:$R$429,MATCH('2'!B42,Daten!$A$7:$A$429,0)) -> 97580839 | F42: =INDEX(Daten!$M$7:$M$429,MATCH('2'!B42,Daten!$A$7:$A$429,0)) -> 39389676 | G42: =INDEX(Daten!$N$7:$N$429,MATCH('2'!B42,Daten!$A$7:$A$429,0)) -> 25056525 | H42: =INDEX(Daten!$P$7:$P$429,MATCH('2'!B42,Daten!$A$7:$A$429,0)) -> 12814034 | I42: =INDEX(Daten!$L$7:$L$429,MATCH('2'!B42,Daten!$A$7:$A$429,0)) -> 6904215.3 | J42: =INDEX(Daten!$K$7:$K$429,MATCH('2'!B42,Daten!$A$7:$A$429,0)) -> 12788882 | K42: =INDEX(Daten!$O$7:$O$429,MATCH('2'!B42,Daten!$A$7:$A$429,0)) -> 627507.56 | L42: =INDEX(Daten!$Q$7:$Q$429,MATCH('2'!B42,Daten!$A$7:$A$429,0)) -> 2041326.8
A43: =Daten!C36 -> JC Elbe-Elster | B43: =Daten!A36 -> 03504 | C43: =Daten!F36 -> 12 | D43: =Daten!E36 -> IIId | E43: =INDEX(Daten!$R$7:$R$429,MATCH('2'!B43,Daten!$A$7:$A$429,0)) -> 61148195 | F43: =INDEX(Daten!$M$7:$M$429,MATCH('2'!B43,Daten!$A$7:$A$429,0)) -> 24732204 | G43: =INDEX(Daten!$N$7:$N$429,MATCH('2'!B43,Daten!$A$7:$A$429,0)) -> 15742993 | H43: =INDEX(Daten!$P$7:$P$429,MATCH('2'!B43,Daten!$A$7:$A$429,0)) -> 7964689.6 | I43: =INDEX(Daten!$L$7:$L$429,MATCH('2'!B43,Daten!$A$7:$A$429,0)) -> 3608379.7 | J43: =INDEX(Daten!$K$7:$K$429,MATCH('2'!B43,Daten!$A$7:$A$429,0)) -> 8779904.7 | K43: =INDEX(Daten!$O$7:$O$429,MATCH('2'!B43,Daten!$A$7:$A$429,0)) -> 320022.77 | L43: =INDEX(Daten!$Q$7:$Q$429,MATCH('2'!B43,Daten!$A$7:$A$429,0)) -> 560948.77
A44: =Daten!C37 -> JC Oberspreewald-Lausitz | B44: =Daten!A37 -> 03506 | C44: =Daten!F37 -> 12 | D44: =Daten!E37 -> IIId | E44: =INDEX(Daten!$R$7:$R$429,MATCH('2'!B44,Daten!$A$7:$A$429,0)) -> 75843103 | F44: =INDEX(Daten!$M$7:$M$429,MATCH('2'!B44,Daten!$A$7:$A$429,0)) -> 30504896 | G44: =INDEX(Daten!$N$7:$N$429,MATCH('2'!B44,Daten!$A$7:$A$429,0)) -> 19540024 | H44: =INDEX(Daten!$P$7:$P$429,MATCH('2'!B44,Daten!$A$7:$A$429,0)) -> 9912761.2 | I44: =INDEX(Daten!$L$7:$L$429,MATCH('2'!B44,Daten!$A$7:$A$429,0)) -> 4200927.2 | J44: =INDEX(Daten!$K$7:$K$429,MATCH('2'!B44,Daten!$A$7:$A$429,0)) -> 11431408 | K44: =INDEX(Daten!$O$7:$O$429,MATCH('2'!B44,Daten!$A$7:$A$429,0)) -> 253086.55 | L44: =INDEX(Daten!$Q$7:$Q$429,MATCH('2'!B44,Daten!$A$7:$A$429,0)) -> 749214.95
... A436: =Daten!C429 -> JC Lichtenberg | B436: =Daten!A429 -> 96208 | C436: =Daten!F429 -> 11 | D436: =Daten!E429 -> IIIb | E436: =INDEX(Daten!$R$7:$R$429,MATCH('2'!B436,Daten!$A$7:$A$429,0)) -> 4.0357338e+08 | F436: =INDEX(Daten!$M$7:$M$429,MATCH('2'!B436,Daten!$A$7:$A$429,0)) -> 1.5061464e+08 | G436: =INDEX(Daten!$N$7:$N$429,MATCH('2'!B436,Daten!$A$7:$A$429,0)) -> 1.3157757e+08 | H436: =INDEX(Daten!$P$7:$P$429,MATCH('2'!B436,Daten!$A$7:$A$429,0)) -> 48913571 | I436: =INDEX(Daten!$L$7:$L$429,MATCH('2'!B436,Daten!$A$7:$A$429,0)) -> 28424274 | J436: =INDEX(Daten!$K$7:$K$429,MATCH('2'!B436,Daten!$A$7:$A$429,0)) -> 42338486 | K436: =INDEX(Daten!$O$7:$O$429,MATCH('2'!B436,Daten!$A$7:$A$429,0)) -> 1704835.4 | L436: =INDEX(Daten!$Q$7:$Q$429,MATCH('2'!B436,Daten!$A$7:$A$429,0)) -> 2131743.5
L437: © Statistik der Bundesagentur für Arbeit
A439: =Steuerung_Eckwerte!I10 -> ¹ Umfasst alle Eingliederungsleistungen nach § 16 ff. SGB II (ohne kommunale Eingliederungsleistungen gem. § 16a SGB II), die durch den Bund erstattungsfähig sind. Die Kosten für die Eignungsfeststellung nach § 16 SGB II in Verbindung mit § 32 SGB III können sowohl über das Verwaltungsbudget als auch als Eingliederungsleistung abgerechnet werden.
A440: =Steuerung_Eckwerte!I11 -> ² Die Ausgaben für überörtliche Verwaltungsaufgaben der BA sowie für sonstige überörtlich wahrzunehmende Aufgaben der BA (z.B. SGB II-Statistik) und Sonderbedarfe (z.B. für Organisationsänderungen gemäß § 6a Absatz 7 SGB II und für die Umsetzung der Bundesprogramme) sind nicht enthalten.
A441: =Steuerung_Eckwerte!I12 -> ³ Die Verwaltungsausgaben beinhalten nicht den kommunalen Finanzierungsanteil.
A442: =Steuerung_Eckwerte!I13 -> ⁴ Für die Leistungen für Bildung und Teilhabe nach § 28 SGB II besteht noch keine vollständige Datenübermittlung. Aus diesem Grund werden die Ausgaben für Bildung und Teilhabe nur nachrichtlich für die einzelnen Jobcenter berichtet und fließen daher auch nicht in die Insgesamtsumme ein. Es werden keine Summen für Deutschland, Westdeutschland, Ostdeutschland und für die Bundesländer gebildet. Ein Vorjahresvergleich ist nur eingeschränkt möglich.
A443: =Steuerung_Eckwerte!I14 -> ⁵ Aufgrund von Änderungen in der Regionalzuordnung von Gemeinden zu Jobcentern ist ein Vergleich mit dem Vorjahr nur eingeschränkt möglich.

Sheet 3
I1: Ausgaben im SGB II
A3: Tabelle 3: Eckwerte der Grundsicherung im SGB II | H3: zurück zum Inhalt
A4: Deutschland, West/Ost und Jobcenter (Gebietsstand Dezember 2024)
A5: Jahresdurchschnitt 2024
E7: Bedarfs- gemein- schaften (BG) | F7: Personen in Bedarfs- gemein- schaften (PERS) | G7: dar. (Sp. 2)
A8: Region | B8: Tr Nr | C8: Bundes- land | D8: Ver- gleichs- typ | G8: Regel- leistungs- berechtigte (RLB) | H8: dav. (Sp. 3)
H9: Erwerbsfähige Leistungs- berechtigte (ELB) | I9: Nicht erwerbsfähige Leistungs- berechtigte (NEF)
E10: 1 | F10: 2 | G10: 3 | H10: 4 | I10: 5
A11: Deutschland | B11: D | C11: D | E11: 2931462.9 | F11: 5766789.8 | G11: 5501028.3 | H11: 3987699.6 | I11: 1513328.7
A12: Westdeutschland | B12: W | C12: W | E12: 2220341.9 | F12: 4460279.8 | G12: 4262943.6 | H12: 3061166.3 | I12: 1201777.2
A13: Ostdeutschland | B13: O | C13: O | E13: 711121 | F13: 1306510 | G13: 1238084.7 | H13: 926533.25 | I13: 311551.42
A14: JC Vorpommern-Greifswald | B14: 03002 | C14: 13 | D14: IIId | E14: 10592.583 | F14: 18498.5 | G14: 17111.833 | H14: 13370.917 | I14: 3740.9167
A15: JC Mecklenburgische Seenplatte Süd | B15: 03102 | C15: 13 | D15: IIId | E15: 7214.9167 | F15: 12801 | G15: 11941.5 | H15: 9079.5 | I15: 2862
A16: JC Mecklenburgische Seenplatte Nord | B16: 03122 | C16: 13 | D16: IIId | E16: 4790.75 | F16: 8188.5 | G16: 7491.5833 | H16: 5845.3333 | I16: 1646.25
A17: JC Rostock, Hansestadt | B17: 03202 | C17: 13 | D17: IIIe | E17: 9801.5833 | F17: 16261.083 | G17: 15243.667 | H17: 11928.5 | I17: 3315.1667
A18: JC Landkreis Rostock | B18: 03208 | C18: 13 | D18: IIIa | E18: 6813.75 | F18: 12325.667 | G18: 11432.25 | H18: 8659.0833 | I18: 2773.1667
A19: JC Schwerin, Landeshauptstadt | B19: 03302 | C19: 13 | D19: IIIe | E19: 6133.5833 | F19: 11336.25 | G19: 10687.75 | H19: 7975.5833 | I19: 2712.1667
A20: JC Nordwestmecklenburg | B20: 03304 | C20: 13 | D20: IIIa | E20: 5266.3333 | F20: 9373.1667 | G20: 8650.75 | H20: 6661.5833 | I20: 1989.1667
A21: JC Ludwigslust-Parchim | B21: 03324 | C21: 13 | D21: IIId | E21: 6332 | F21: 11712.5 | G21: 10792.917 | H21: 8074.3333 | I21: 2718.5833
A22: JC Vorpommern-Rügen | B22: 03444 | C22: 13 | D22: IIId | E22: 9495.0833 | F22: 16003.5 | G22: 15395.75 | H22: 11828.25 | I22: 3567.5
A23: JC Cottbus, Stadt | B23: 03502 | C23: 12 | D23: IIIe | E23: 5610.1667 | F23: 10229.5 | G23: 9652.0833 | H23: 7171.0833 | I23: 2481
A24: JC Elbe-Elster | B24: 03504 | C24: 12 | D24: IIId | E24: 3612 | F24: 6237.4167 | G24: 5849.1667 | H24: 4476.6667 | I24: 1372.5
A25: JC Oberspreewald-Lausitz | B25: 03506 | C25: 12 | D25: IIId | E25: 4491.75 | F25: 7801.4167 | G25: 7284.0833 | H25: 5624.8333 | I25: 1659.25
... A417: JC Lichtenberg | B417: 96208 | C417: 11 | D417: IIIb | E417: 20397.25 | F417: 40107.75 | G417: 38002 | H417: 27009 | I417: 10993
I418: © Statistik der Bundesagentur für Arbeit

Sheet 4
I1: Ausgaben im SGB II
H3: zurück zum Inhalt
A6: Die Statistik der Bundesagentur für Arbeit berichtet seit 2005 im Rahmen der Grundsicherungsstatistik über passive Leistungen zum Lebensunterhalt aus dem SGB II an Bedarfsgemeinschaften und Personen. Diese Zahlungsansprüche finden grundsätzlich als Summen ihre Entsprechung in den Ausgaben eines Trägers. Die Summe der Zahlungsansprüche aus der Leistungsstatistik SGB II und die Ausgabensummen aus den Haushaltsdaten der Träger sind allerdings aufgrund von mess- und zähltechnischen Unterschieden nicht identisch:
A12: Bestandskonzept versus Zahlungsfluss: Während die Leistungsstatistik SGB II ausschließlich Zahlungsansprüche von Bedarfsgemeinschaften summiert, die zum statistischen Stichtag (Mitte des Monats) bestandsrelevant waren, bezieht die Ausgabensumme in der Regel alle Ausgaben eines Zeitraums ein, also auch für BG, die nicht bestandsrelevant waren.
A16: Zeitliche Zuordnung: Die Leistungsstatistik SGB II ordnet Zahlungsansprüche dem Bedarfsmonat zu, während sich die Zählung von Ausgaben in der Regel am Zeitpunkt des Geldflusses orientiert. Nachzahlungen für mehrere nachbewilligte Leistungsmonate werden somit bei den Ausgaben im Zahlmonat als Summe ausgewiesen, in der Leistungsstatistik SGB II im jeweiligen Bedarfsmonat.
A21: Wartezeitkonzept: Ergebnisse der Leistungsstatistik SGB II werden mit einer Wartezeit von 3 Monaten festgeschrieben, während zahlungsrelevante Änderungen in der Regel in der Ausgabensumme am aktuellen Rand aufgeführt werden.
A24: In diesem Produkt „Ausgaben im SGB II“ werden zum Vergleich und zur besseren Einschätzbarkeit hier die Summen der Zahlungsansprüche aus der Statistik über passive Leistungen aus dem SGB II des Jahres 2024 dargestellt. Die Aggregation der Zahlungsansprüche erfolgt spiegelbildlich zu den Kategorien der Ausgaben in Tabelle 1 und 2. Dies weicht geringfügig von den Darstellungen der Grundsicherungsstatistik SGB II ab.
A30: Tabelle 4: Zahlungsanspüche im SGB II
A31: Deutschland, West/Ost und Jobcenter (Gebietsstand Dezember 2024)
A32: Jahressumme 2024
E34: Zahlungs- ansprüche insgesamt 1) | F34: dav. (Sp. 1)
A35: Region | B35: Tr Nr | C35: Bundes- land | D35: Ver- gleichs- typ | F35: Regelbedarfe, Mehrbedarfe, unabweisbarer Bedarf 2) | G35: Kosten der Unterkunft | H35: Abweichend zu erbringende Leistungen | I35: Zahlungs- ansprüche für Leistungen zur Sozialver- sicherung
E36: 1 | F36: 2 | G36: 3 | H36: 4 | I36: 5
A37: Deutschland | B37: D | C37: D | E37: 4.6920954e+10 | F37: 2.193585e+10 | G37: 1.768482e+10 | H37: 2.4845281e+08 | I37: 7.0518316e+09
A38: Westdeutschland | B38: W | C38: W | E38: 3.6184795e+10 | F38: 1.6797852e+10 | G38: 1.37959e+10 | H38: 1.8368462e+08 | I38: 5.4073584e+09
A39: Ostdeutschland | B39: O | C39: O | E39: 1.0736159e+10 | F39: 5.1379983e+09 | G39: 3.8889196e+09 | H39: 64768195 | I39: 1.6444732e+09
A40: JC Vorpommern-Greifswald | B40: 03002 | C40: 13 | D40: IIId | E40: 1.452531e+08 | F40: 74189227 | G40: 46423786 | H40: 1001849.9 | I40: 23638239
A41: JC Mecklenburgische Seenplatte Süd | B41: 03102 | C41: 13 | D41: IIId | E41: 1.0030426e+08 | F41: 51265385 | G41: 32136476 | H41: 854553.71 | I41: 16047842
A42: JC Mecklenburgische Seenplatte Nord | B42: 03122 | C42: 13 | D42: IIId | E42: 63515545 | F42: 32389462 | G42: 20327316 | H42: 446990.57 | I42: 10351777
A43: JC Rostock, Hansestadt | B43: 03202 | C43: 13 | D43: IIIe | E43: 1.3424367e+08 | F43: 64788606 | G43: 47259061 | H43: 1001938.6 | I43: 21194067
A44: JC Landkreis Rostock | B44: 03208 | C44: 13 | D44: IIIa | E44: 97084661 | F44: 48587121 | G44: 32604769 | H44: 533898.91 | I44: 15358873
A45: JC Schwerin, Landeshauptstadt | B45: 03302 | C45: 13 | D45: IIIe | E45: 90056215 | F45: 45091532 | G45: 29702184 | H45: 1103623.8 | I45: 14158874
A46: JC Nordwestmecklenburg | B46: 03304 | C46: 13 | D46: IIIa | E46: 72362094 | F46: 36811334 | G46: 23416023 | H46: 308350.15 | I46: 11826388
A47: JC Ludwigslust-Parchim | B47: 03324 | C47: 13 | D47: IIId | E47: 88067139 | F47: 46000691 | G47: 27065277 | H47: 689037.55 | I47: 14312133
A48: JC Vorpommern-Rügen | B48: 03444 | C48: 13 | D48: IIId | E48: 1.3206601e+08 | F48: 65970221 | G48: 44225289 | H48: 1058330.1 | I48: 20812173
A49: JC Cottbus, Stadt | B49: 03502 | C49: 12 | D49: IIIe | E49: 78949912 | F49: 39730773 | G49: 25901782 | H49: 620035.86 | I49: 12697322
A50: JC Elbe-Elster | B50: 03504 | C50: 12 | D50: IIId | E50: 49674009 | F50: 25304002 | G50: 16109114 | H50: 324719 | I50: 7936174.2
A51: JC Oberspreewald-Lausitz | B51: 03506 | C51: 12 | D51: IIId | E51: 61371264 | F51: 31054492 | G51: 20121609 | H51: 245617.28 | I51: 9949545.5
... A239: JC Gießen | B239: 42702 | C239: 06 | D239: IId | E239: 1.9146704e+08 | F239: 86449961 | G239: 75592962 | H239: 1557037 | I239: 27867083
A240: JC Vogelsbergkreis | B240: 42704 | C240: 06 | D240: IIa | E240: 0 | F240: . | G240: . | H240: . | I240: .
A241: JC Wetteraukreis | B241: 42708 | C241: 06 | D241: IId | E241: 1.3112992e+08 | F241: 60021983 | G241: 50685525 | H241: 658542.82 | I241: 19763872
A242: JC Main-Kinzig-Kreis | B242: 43102 | C242: 06 | D242: IId | E242: 2.3346195e+08 | F242: 1.0796667e+08 | G242: 90504852 | H242: 1788797.2 | I242: 33201630
A243: JC Hochtaunuskreis | B243: 43302 | C243: 06 | D243: IIe | E243: 96386024 | F243: 44375467 | G243: 37783612 | H243: 397964.22 | I243: 13828981
A244: JC Main-Taunus-Kreis | B244: 43304 | C244: 06 | D244: IIe | E244: 1.1045728e+08 | F244: 45805874 | G244: 49483983 | H244: 478281.67 | I244: 14689137
A245: JC Groß-Gerau | B245: 43306 | C245: 06 | D245: IIe | E245: 1.719624e+08 | F245: 74888177 | G245: 71416204 | H245: 718763.12 | I245: 24939253
A246: JC Kassel, documenta-Stadt | B246: 43502 | C246: 06 | D246: IIIb | E246: 1.9696943e+08 | F246: 92254498 | G246: 73691153 | H246: 1129453.7 | I246: 29894324
A247: JC Kassel | B247: 43504 | C247: 06 | D247: IId | E247: 93418382 | F247: 45694218 | G247: 33100839 | H247: 463175.27 | I247: 14160150
A248: JC Werra-Meißner-Kreis | B248: 43520 | C248: 06 | D248: IIa | E248: 44629222 | F248: 22754306 | G248: 14386126 | H248: 366404.32 | I248: 7122386.2
A249: JC Waldeck-Frankenberg | B249: 43902 | C249: 06 | D249: Ie | E249: 62045252 | F249: 30580989 | G249: 21685191 | H249: 416597.05 | I249: 9362474.8
A250: JC Schwalm-Eder-Kreis | B250: 43904 | C250: 06 | D250: IIa | E250: 67472577 | F250: 34258732 | G250: 22099486 | H250: 563194.53 | I250: 10551164
A251: JC Limburg-Weilburg | B251: 44302 | C251: 06 | D251: IIc | E251: 86723049 | F251: 40424700 | G251: 32549062 | H251: 664281.5 | I251: 13085006
A252: JC Lahn-Dill-Kreis | B252: 44304 | C252: 06 | D252: IId | E252: 1.4916022e+08 | F252: 70602568 | G252: 55173136 | H252: 1287556.1 | I252: 22096963
... A443: JC Lichtenberg | B443: 96208 | C443: 11 | D443: IIIb | E443: 3.3224603e+08 | F443: 1.4879779e+08 | G443: 1.3365796e+08 | H443: 1957341.8 | I443: 47832929
I444: © Statistik der Bundesagentur für Arbeit
A446: ¹ Aufgrund der Vergleichbarkeit mit Tabelle 1 und 2 weichen die Zahlungsansprüche geringfügig von anderweitig veröffentlichten Zahlungsansprüchen in der Grundsicherungsstatistik SGB II ab.
A447: 2 Die Einmalleistungen nach § 70 und 71 SGB II (Einmalzahlung aus Anlass der COVID-19-Pandemie und Kinderfreizeitbonus und weitere Regelung aus Anlass der COVID-19-Pandemie) sind im Gegensatz zu den Ausgaben nicht in den Zahlungsansprüchen für Arbeitslosengeld II / Sozialgeld enthalten.

Sheet Methodische Hinweise
H1: Ausgaben im SGB II
H2: Stand: 17.11.2025
A4: Methodische Hinweise | G4: zurück zum Inhalt
A5: Ausgaben für aktive und passive Leistungen im SGB II 2024
A8: Abkürzungen
A10: . | B10: Fehlende Werte bei einzelnen Trägern können wegen unplausibler beziehungsweise unvollständiger Datenlage auftreten.
A11: X | B11: Nachweis ist nicht sinnvoll
A12: .X | B12: Veränderungswert >250% bzw. Veränderungswert <-250%
A14: Allgemeine Hinweise
A16: Die Ausgaben für aktive und passive Leistungen sind die tatsächlich erbrachten Zahlungen der Jobcenter. Das heißt, dass Rückeinnahmen den Ausgaben zufließen. Dies können zum Beispiel zu viel geleistete Ausgaben (Rückzahlung aufgrund der Unrechtmäßigkeit einer Zahlung, zum Beispiel Doppelzahlung, Überzahlung) sein.
A18: Gebietsstand
A20: Die Daten beziehen sich auf den Gebietsstand zum Dezember 2024.
A22: Datenquellen
A24: Für Jobcenter in gemeinsamer Einrichtung:
A26: Finanzsysteme der Bundesagentur für Arbeit (BA)
A28: Die Daten für Deutschland beinhalten die Buchungen der Jobcenter zuzüglich der Buchungen der Regionaldirektionen, der besonderen Dienststellen und SGB III-Dienststellen (BA) auf Finanzpositionen des SGB II.
A30: Die Daten für Ost- und Westdeutschland sowie der Bundesländer beinhalten die Buchungen der Jobcenter zuzüglich der Buchungen der SGB III-Dienststellen (BA) auf Finanzpositionen des SGB II. Buchungen der besonderen Dienststellen sowie der Regionaldirektionen sind nicht enthalten.
A32: Für Jobcenter in zugelassener kommunaler Trägerschaft:
A34: Datenstandard XSozial-BA-SGB II
A36: Aktuelle Version unter:
... A53: http://doku.iab.de/forschungsbericht/2013/fb1113.pdf

Sheet Glossar
H1: Ausgaben im SGB II
H2: Stand: 17.11.2025
A4: Glossar | G4: zurück zum Inhalt
A5: Ausgaben für aktive und passive Leistungen im SGB II 2024
A6: Seite 1/3
A8: Bürgergeld (Bundesleistung)
A10: Bürgergeld ist die Gesamtregelleistung zur Sicherung des Lebensunterhalts nach dem SGB II. Man unterscheidet zwischen Bürgergeld für erwerbsfähige Leistungsberechtigte nach § 19 Absatz 1 Satz 1 SGB II (Bürgergeld für ELB, vor 2023: Arbeitslosengeld II) und Bürgergeld für nicht erwerbsfähige Leistungsberechtigte nach § 19 Absatz 1 Satz 2 SGB II (Bürgergeld für NEF, vor 2023: Sozialgeld).
A12: Die Ausgaben für Bürgergeld (ohne Kosten der Unterkunft) beinhalten folgende Bundesleistungen:
B14: ■ Regelbedarf nach § 20 SGB II
B15: ■ Befristeter Zuschlag nach dem Bezug von Arbeitslosengeld (Rechtsgrundlage entfallen zum 01.01.2011)
B16: ■ Darlehensweise Geldleistungen bzw. Anschaffung von Sachleistungen nach § 24 Abs. 1 SGB II
B17: ■ Leistungen für Mehrbedarfe beim Lebensunterhalt für werdende Mütter nach § 21 Abs. 2 SGB II
B18: ■ Leistungen für Mehrbedarfe beim Lebensunterhalt für Alleinerziehende nach § 21 Abs. 3 SGB II
B19: ■ Leistungen für Mehrbedarfe beim Lebensunterhalt für erwerbsfähige Leistungsberechtigte mit Behinderung nach § 21 Abs. 4 SGB II
B20: ■ Leistungen für Mehrbedarfe beim Lebensunterhalt für nicht erwerbsfähige Leistungsberechtigte mit Behinderung nach §19 Abs. 1 S. 2 i.V.m. §23 Nr.2 SGB II
B21: ■ Leistungen für Mehrbedarfe beim Lebensunterhalt für kostenaufwändige Ernährung nach § 21 Abs. 5 SGB II
B22: ■ Unabweisbare besondere Bedarfe, die in atypischen Lebenslagen anfallen nach § 21 Abs. 6 SGB II
B23: ■ Leistungen für Mehrbedarfe - Energie und Warmwasser nach § 21 Abs. 7 SGB II
B24: ■ Leistungen für Mehrbedarfe - Schulbuchförderung nach § 21 Abs. 6a SGB II
B25: ■ Einmalzahlung aus Anlass der COVID-19-Pandemie nach § 70, 73 SGB II
... B28: ■ Teilhabe am Arbeitsmarkt § 16i SGB II - Zuschuss zum Arbeitsentgelt
A30: Die Zahlungsrückläufe und Rückeinnahmen aus dem Forderungseinzug von Bundesleistungen in den Finanzsystemen der BA aus früheren Jahren werden vom Bürgergeld abgezogen. Die Buchungssummen belaufen sich im Jahr 2024 bundesweit auf 3.001.302,47.
A32: Nicht berücksichtigt werden die Zuschüsse zu orthopädischen Schuhen, therapeutischen Geräten, Ausrüstungen sowie Miete von therapeutischen Ausrüstungen. In den Finanzsystemen der BA wurden im Jahr 2024 insgesamt 81.295,43 Euro erfasst.
A35: Kosten der Unterkunft
A37: Unter den Kosten der Unterkunft werden folgende Ausgaben zusammengefasst:
B39: ■ Leistungen für Unterkunft und Heizung
B40: ■ Wohnungsbeschaffungskosten, Mietkaution, Umzugskosten
B41: ■ Übernahme der Mietschulden
B42: ■ Zuschuss zu den Leistungen für Unterkunft und Heizung bei ausgeschlossenen Auszubildenden
B43: ■ Zuschuss zu Genossenschaftsanteilen
B44: ■ Zuschuss Instandhaltung und Reparatur bei selbstgenutztem Wohneigentum
B45: ■ Darlehensweise Übernahme der Leistungen für Unterkunft und Heizung
B46: ■ Darlehensweise Übernahme der Wohnungsbeschaffungskosten, Mietkaution, Umzugskosten
B47: ■ Darlehensweise Übernahme der Mietschulden
B48: ■ Darlehensweise Übernahme des Zuschusses zu den Leistungen für Unterkunft und Heizung bei ausgeschlossenen Auszubildenden
B49: ■ Darlehensweise Übernahme von Genossenschaftsanteilen
B50: ■ Darlehen Instandhaltung und Reparatur bei selbstgenutzem Wohneigentum
... B56: ■ Tilgungen der darlehensweisen Übernahme von Instandhaltung und Reparatur von selbstgenutzem Wohneigentum
A59: Leistungen zur Sozialversicherung
A61: Bei den Leistungen zur Sozialversicherung handelt es sich um folgende Leistungen:
B63: ■ Krankenversicherungsbeiträge
B64: ■ Rentenversicherungsbeiträge (Rechtsgrundlage entfallen zum 01.01.2011)
B65: ■ Pflegeversicherungsbeiträge
B66: ■ Säumniszuschläge Krankenversicherungsbeiträge
B67: ■ Säumniszuschläge Rentenversicherungsbeiträge (Rechtsgrundlage entfallen zum 01.01.2011)
B68: ■ Säumniszuschläge Pflegeversicherungsbeiträge
B69: ■ Durchschnittlicher Zusatzbeitrag zur Krankenversicherung
B70: ■ Zuschüsse zu den Beiträgen zur privaten, gesetzlichen oder freiwillig gesetzlichen Krankenversicherung
B71: ■ Zuschüsse zu den Beiträgen bei Befreiung von der Versicherungspflicht in der gesetzlichen Rentenversicherung (Rechtsgrundlage entfallen zum 01.01.2011)
B72: ■ Zuschüsse zu den Beiträgen zur privaten und sozialen Pflegeversicherung
B73: ■ Zuschüsse zur privaten, gesetzlichen oder freiwillig gesetzlichen Krankenversicherung zur Vermeidung von Hilfebedürftigkeit
B74: ■ Zuschüsse zur privaten und sozialen Pflegeversicherung zur Vermeidung von Hilfebedürftigkeit
B75: ■ Zusatzbeiträge zur gesetzlichen oder freiwillig gesetzlichen Krankenversicherung zur Vermeidung von Hilfebedürftigkeit (ab dem 01.01.2017 in den Zuschüssen zur gesetzlichen Krankenversicherung enthalten)
A78: Seite 2/3
A80: Bei Bezug von Bürgergeld werden die Beiträge zur gesetzlichen Kranken- und Pflegeversicherung vom Träger der Grundsicherung direkt an den Sozialversicherungsträger überwiesen. War der Bürgergeld-Empfänger unmittelbar vor Beginn des Bezugs von Bürgergeld privat krankenversichert, kann max. der halbierte Beitrag im sog. Basistarif zur privaten Krankenversicherung als Zuschuss plus die Aufwendungen für eine private Pflegeversicherung übernommen werden.
A82: Bei Bezug von Bürgergeld besteht keine Pflichtversicherung in der gesetzlichen Rentenversicherung. Die Zeit des Bezugs wird jedoch durch das zuständige Jobcenter an die Rentenversicherung übermittelt, die dann prüft, ob eine Anrechnungszeit vorliegt.
A85: Eingliederungsleistungen
A87: Die Ausgaben für Eingliederungsleistungen umfassen folgende Maßnahmen der aktiven Arbeitsmarktpolitik:
A89: Aktivierung und berufliche Eingliederung
B91: ■ Vermittlungsbudget
B92: ■ Maßnahmen zur Aktivierung und beruflichen Eingliederung
B93: ■ Probebeschäftigung für Menschen mit Behinderungen
B94: ■ Arbeitshilfen für Menschen mit Behinderungen
B95: ■ Förderung schwer zu erreichender junger Menschen
B96: ■ Ganzheitliche Betreuung
A98: Berufswahl und Berufsausbildung
B100: ■ Assistierte Ausbildung
B101: ■ Ausbildungsbegleitende Hilfen
B102: ■ Außerbetriebliche Berufsausbildung
B103: ■ Zuschüsse zur Ausbildungsvergütung für Menschen mit Behinderungen und schwerbehinderte Menschen
B104: ■ Einstiegsqualifizierung
B105: ■ Berufsorientierungspraktikum
B106: ■ Mobilitätszuschuss
B107: ■ Zuschuss für schwerbehinderte Menschen im Anschluss an Aus- und Weiterbildung
A109: Berufliche Weiterbildung
B111: ■ Förderung der beruflichen Weiterbildung
B112: ■ Rehabilitanden in Förderung der beruflichen Weiterbildung
B113: ■ Arbeitsentgeltzuschuss bei beruflicher Weiterbildung Beschäftigter
A115: Aufnahme einer Erwerbstätigkeit
B117: ■ Eingliederungszuschuss
B118: ■ Eingliederungszuschuss für besonders betroffene schwerbehinderte Menschen
B119: ■ Einstiegsgeld bei abhängiger sozialversicherungspflichtiger Erwerbstätigkeit
B120: ■ Beschäftigungszuschuss (Restabwicklung)
B121: ■ Einstiegsgeld bei selbständiger Erwerbstätigkeit
B122: ■ Eingliederung von Langzeitarbeitslosen
B123: ■ Leistungen zur Eingliederung von Selbständigen
A125: besondere Maßnahmen zur Teilhabe von Menschen mit Behinderungen
B127: ■ besondere Maßnahmen zur beruflichen Weiterbildung von Menschen mit Behinderungen
A129: Beschäftigung schaffende Maßnahmen
B131: ■ Arbeitsgelegenheiten
B132: ■ Förderung von Arbeitsverhältnissen
B133: ■ Teilhabe am Arbeitsmarkt
A135: Freie Förderung
B137: ■ Freie Förderung SGB II
A139: Sonstige Förderung
B141: ■ Bürgergeldbonus
B142: ■ Reisekosten
B143: ■ Erstattungen von Leistungen zur Rehabilitation an öffentlich-rechtliche Träger
B144: ■ Zuschüsse i. R. d. Sicherstellungsauftrags Sozialdienstleister-Einsatz-Gesetz
B145: ■ Hochwasserhilfe
...

Sheet Statistik-Infoseite
G2: Stand: 11.04.2025
A3: Statistik-Infoseite
A6: Im Internet stehen statistische Informationen zu diesen Themen zur Verfügung:
B8: Fachstatistiken:
B9: Arbeitsuche, Arbeitslosigkeit und Unterbeschäftigung
B10: Ausbildungsmarkt
B11: Beschäftigung
B12: Einnahmen/Ausgaben
B13: Förderung und berufliche Rehabilitation
B14: Gemeldete Arbeitsstellen
B15: Grundsicherung für Arbeitsuchende (SGB II)
B16: Leistungen SGB III
B18: Themen im Fokus:
B19: Berufe
B20: Bildung
... B26: Frauen und Männer
A27: Jüngere | B27: Jüngere
B28: Langzeitarbeitslosigkeit
B29: Menschen mit Behinderungen
B30: Migration
B31: Regionale Mobilität
B32: Transformation
B33: Ukraine-Krieg
B34: Wirtschaftszweige
B35: Zeitarbeit
A37: Die Methodischen Hinweise der Statistik bieten ergänzende Informationen.
A39: Die Qualitätsberichte der Statistik erläutern die Entstehung und Aussagekraft der jeweiligen Fachstatistik.
A41: Das Glossar enthält Erläuterungen zu allen statistisch relevanten Begriffen, die in den verschiedenen Produkten der Statistik der BA Verwendung finden.
A44: Abkürzungen und Zeichen, die in den Produkten der Statistik der BA vorkommen, werden im
A45: Abkürzungsverzeichnis | C45: bzw. der Zeichenerklärung der Statistik der BA erläutert.

Sheet Steuerung_Eckwerte
A1: Region für die Auswahlliste (ohne Gebietsstand) (Trägernummer und Trägerbezeichnung im gelben Bereich sind zu aktualisieren) | C1: Region für die Tabellenüberschrift (Formeln im grünen Bereich müssen i.d.R. nicht angepasst werden) | D1: Gebietsstand | E1: Hinweise über der Tabelle | F1: Fußnote in der Regionen- bezeichnung (Formeln im grünen Bereich müssen i.d.R. nicht angepasst werden) | H1: Hinweise und Fußnoten (Text und Nummerierung hier anpassen)
B3: =INDEX(B6:B428,C4) -> Deutschland | C3: =INDEX(C6:C428,C4) -> Deutschland | D3: (Gebietsstand Dezember 2024) | E3: =INDEX(E6:E428,C4) -> H1 | F3: =INDEX(F6:F428,C4) -> 0 | H3: Hinweise über der Tabelle
C4: 1 | H4: H1 | I4: Die Daten für Deutschland insgesamt beinhalten die Buchungen der Jobcenter zuzüglich der Buchungen der Regionaldirektionen, der besonderen Dienststellen und SGB III-Dienststellen (BA) auf Finanzpositionen des SGB II.
H5: H2 | I5: Die Daten für Ost- und Westdeutschland sowie der Bundesländer beinhalten die Buchungen der Jobcenter zuzüglich der Buchungen der SGB III-Dienststellen (BA) auf Finanzpositionen des SGB II. Buchungen der besonderen Dienststellen sowie der Regionaldirektionen sind nicht enthalten.
A6: D | B6: Deutschland | C6: Deutschland | E6: H1 | H6: H3 | I6: Mit Ausnahme der Ausgaben für Bildung und Teilhabe wurden die Informationen für Deutschland, Ost- und Westdeutschland sowie die Bundesländer um die unplausiblen bzw. nicht vorhandenen Daten einzelner Jobcenter hochgerechnet. Für unplausible bzw. unvollständige Datenlieferungen im Bereich Eingliederungsleistungen wird bereits auf Jobcenter-Ebene ein Schätzwert gebildet.
A7: W | B7: Westdeutschland | C7: Westdeutschland | E7: H2
A8: O | B8: Ostdeutschland | C8: Ostdeutschland | E8: H2
A9: 01 | B9: Schleswig-Holstein | C9: Schleswig-Holstein | E9: H2 | H9: Fußnoten unter der Tabelle
A10: 02 | B10: Hamburg | C10: Hamburg | E10: H2 | H10: ¹ | I10: ¹ Umfasst alle Eingliederungsleistungen nach § 16 ff. SGB II (ohne kommunale Eingliederungsleistungen gem. § 16a SGB II), die durch den Bund erstattungsfähig sind. Die Kosten für die Eignungsfeststellung nach § 16 SGB II in Verbindung mit § 32 SGB III können sowohl über das Verwaltungsbudget als auch als Eingliederungsleistung abgerechnet werden.
A11: 03 | B11: Niedersachsen | C11: Niedersachsen | E11: H2 | H11: ² | I11: ² Die Ausgaben für überörtliche Verwaltungsaufgaben der BA sowie für sonstige überörtlich wahrzunehmende Aufgaben der BA (z.B. SGB II-Statistik) und Sonderbedarfe (z.B. für Organisationsänderungen gemäß § 6a Absatz 7 SGB II und für die Umsetzung der Bundesprogramme) sind nicht enthalten.
A12: 04 | B12: Bremen | C12: Bremen | E12: H2 | H12: ³ | I12: ³ Die Verwaltungsausgaben beinhalten nicht den kommunalen Finanzierungsanteil.
A13: 05 | B13: Nordrhein-Westfalen | C13: Nordrhein-Westfalen | E13: H2 | H13: ⁴ | I13: ⁴ Für die Leistungen für Bildung und Teilhabe nach § 28 SGB II besteht noch keine vollständige Datenübermittlung. Aus diesem Grund werden die Ausgaben für Bildung und Teilhabe nur nachrichtlich für die einzelnen Jobcenter berichtet und fließen daher auch nicht in die Insgesamtsumme ein. Es werden keine Summen für Deutschland, Westdeutschland, Ostdeutschland und für die Bundesländer gebildet. Ein Vorjahresvergleich ist nur eingeschränkt möglich.
A14: 06 | B14: Hessen | C14: Hessen | E14: H2 | H14: ⁵ | I14: ⁵ Aufgrund von Änderungen in der Regionalzuordnung von Gemeinden zu Jobcentern ist ein Vergleich mit dem Vorjahr nur eingeschränkt möglich.
A15: 07 | B15: Rheinland-Pfalz | C15: Rheinland-Pfalz | E15: H2
A16: 08 | B16: Baden-Württemberg | C16: Baden-Württemberg | E16: H2
A17: 09 | B17: Bayern | C17: Bayern | E17: H2
A18: 10 | B18: Saarland | C18: Saarland | E18: H2
A19: 11 | B19: Berlin | C19: Berlin | E19: H2
A20: 12 | B20: Brandenburg | C20: Brandenburg | E20: H2 | H20: Nicht verwendete Standard-Fußnoten
A21: 13 | B21: Mecklenburg-Vorpommern | C21: Mecklenburg-Vorpommern | E21: H2
A22: 14 | B22: Sachsen | C22: Sachsen | E22: H2 | H22: ⁷ | I22: ⁷ Aufgrund einer Mischkreisfusion mit neuer Trägerschaft gE und der damit verbundenen teilweisen Umstellungsprozesse in der Datenübermittlung ist der Vorjahresvergleich der Ausgaben eingeschränkt.
A23: 15 | B23: Sachsen-Anhalt | C23: Sachsen-Anhalt | E23: H2 | H23: ⁶ | I23: ⁶ Trägerfusion: Die Daten beziehen sich auf den Gebietsstand zum Dezember 2022. Die Daten für das Jahr 2021 wurden auf den neuen Gebietsstand umgerechnet.
A24: 16 | B24: Thüringen | C24: Thüringen | E24: H2
A25: 51906 | B25: JC Ahrweiler | C25: =CONCATENATE(B25, " ", $D$3, " ", F25) -> JC Ahrweiler (Gebietsstand Dezember 2024) | F25: =IF(INDEX(Daten!$H$26:$H$429,MATCH(Steuerung_Eckwerte!B25,Daten!$C$26:$C$429,0))=0, " ", INDEX(Daten!$H$26:$H$429,MATCH(Steuerung_Eckwerte!B25,Daten!$C$26:$C$429,0)))
A26: 81102 | B26: JC Aichach-Friedberg | C26: =CONCATENATE(B26, " ", $D$3, " ", F26) -> JC Aichach-Friedberg (Gebietsstand Dezember 2024) | F26: =IF(INDEX(Daten!$H$26:$H$429,MATCH(Steuerung_Eckwerte!B26,Daten!$C$26:$C$429,0))=0, " ", INDEX(Daten!$H$26:$H$429,MATCH(Steuerung_Eckwerte!B26,Daten!$C$26:$C$429,0)))
A27: 68404 | B27: JC Alb-Donau-Kreis | C27: =CONCATENATE(B27, " ", $D$3, " ", F27) -> JC Alb-Donau-Kreis (Gebietsstand Dezember 2024) | F27: =IF(INDEX(Daten!$H$26:$H$429,MATCH(Steuerung_Eckwerte!B27,Daten!$C$26:$C$429,0))=0, " ", INDEX(Daten!$H$26:$H$429,MATCH(Steuerung_Eckwerte!B27,Daten!$C$26:$C$429,0)))
A28: 09418 | B28: JC Altenburger Land | C28: =CONCATENATE(B28, " ", $D$3, " ", F28) -> JC Altenburger Land (Gebietsstand Dezember 2024) | F28: =IF(INDEX(Daten!$H$26:$H$429,MATCH(Steuerung_Eckwerte!B28,Daten!$C$26:$C$429,0))=0, " ", INDEX(Daten!$H$26:$H$429,MATCH(Steuerung_Eckwerte!B28,Daten!$C$26:$C$429,0)))
A29: 54702 | B29: JC Altenkirchen (Westerwald) | C29: =CONCATENATE(B29, " ", $D$3, " ", F29) -> JC Altenkirchen (Westerwald) (Gebietsstand Dezember 2024) | F29: =IF(INDEX(Daten!$H$26:$H$429,MATCH(Steuerung_Eckwerte!B29,Daten!$C$26:$C$429,0))=0, " ", INDEX(Daten!$H$26:$H$429,MATCH(Steuerung_Eckwerte!B29,Daten!$C$26:$C$429,0)))
A30: 04846 | B30: JC Altmarkkreis Salzwedel | C30: =CONCATENATE(B30, " ", $D$3, " ", F30) -> JC Altmarkkreis Salzwedel (Gebietsstand Dezember 2024) | F30: =IF(INDEX(Daten!$H$26:$H$429,MATCH(Steuerung_Eckwerte!B30,Daten!$C$26:$C$429,0))=0, " ", INDEX(Daten!$H$26:$H$429,MATCH(Steuerung_Eckwerte!B30,Daten!$C$26:$C$429,0)))
A31: 85906 | B31: JC Altötting | C31: =CONCATENATE(B31, " ", $D$3, " ", F31) -> JC Altötting (Gebietsstand Dezember 2024) | F31: =IF(INDEX(Daten!$H$26:$H$429,MATCH(Steuerung_Eckwerte!B31,Daten!$C$26:$C$429,0))=0, " ", INDEX(Daten!$H$26:$H$429,MATCH(Steuerung_Eckwerte!B31,Daten!$C$26:$C$429,0)))
A32: 52704 | B32: JC Alzey-Worms | C32: =CONCATENATE(B32, " ", $D$3, " ", F32) -> JC Alzey-Worms (Gebietsstand Dezember 2024) | F32: =IF(INDEX(Daten!$H$26:$H$429,MATCH(Steuerung_Eckwerte!B32,Daten!$C$26:$C$429,0))=0, " ", INDEX(Daten!$H$26:$H$429,MATCH(Steuerung_Eckwerte!B32,Daten!$C$26:$C$429,0)))
A33: 74302 | B33: JC Amberg-Sulzbach | C33: =CONCATENATE(B33, " ", $D$3, " ", F33) -> JC Amberg-Sulzbach (Gebietsstand Dezember 2024) | F33: =IF(INDEX(Daten!$H$26:$H$429,MATCH(Steuerung_Eckwerte!B33,Daten!$C$26:$C$429,0))=0, " ", INDEX(Daten!$H$26:$H$429,MATCH(Steuerung_Eckwerte!B33,Daten!$C$26:$C$429,0)))
A34: 26112 | B34: JC Ammerland | C34: =CONCATENATE(B34, " ", $D$3, " ", F34) -> JC Ammerland (Gebietsstand Dezember 2024) | F34: =IF(INDEX(Daten!$H$26:$H$429,MATCH(Steuerung_Eckwerte!B34,Daten!$C$26:$C$429,0))=0, " ", INDEX(Daten!$H$26:$H$429,MATCH(Steuerung_Eckwerte!B34,Daten!$C$26:$C$429,0)))
A35: 04208 | B35: JC Anhalt-Bitterfeld | C35: =CONCATENATE(B35, " ", $D$3, " ", F35) -> JC Anhalt-Bitterfeld (Gebietsstand Dezember 2024) | F35: =IF(INDEX(Daten!$H$26:$H$429,MATCH(Steuerung_Eckwerte!B35,Daten!$C$26:$C$429,0))=0, " ", INDEX(Daten!$H$26:$H$429,MATCH(Steuerung_Eckwerte!B35,Daten!$C$26:$C$429,0)))
A36: 71146 | B36: JC Ansbach | C36: =CONCATENATE(B36, " ", $D$3, " ", F36) -> JC Ansbach (Gebietsstand Dezember 2024) | F36: =IF(INDEX(Daten!$H$26:$H$429,MATCH(Steuerung_Eckwerte!B36,Daten!$C$26:$C$429,0))=0, " ", INDEX(Daten!$H$26:$H$429,MATCH(Steuerung_Eckwerte!B36,Daten!$C$26:$C$429,0)))
... A428: 09202 | B428: JC Zwickau | C428: =CONCATENATE(B428, " ", $D$3, " ", F428) -> JC Zwickau (Gebietsstand Dezember 2024) | F428: =IF(INDEX(Daten!$H$26:$H$429,MATCH(Steuerung_Eckwerte!B428,Daten!$C$26:$C$429,0))=0, " ", INDEX(Daten!$H$26:$H$429,MATCH(Steuerung_Eckwerte!B428,Daten!$C$26:$C$429,0)))

Sheet Daten
A1: Ausgaben für aktive und passive Leistungen im SGB II
A2: Deutschland, West/Ost, Länder und Jobcenter (Gebietsstand Dezember 2024)
A3: 2024
A5: Region | I5: Gebietsstandsänderung 2023 zu 2024 | K5: 2024 | S5: 2023 | AA5: Veränderung 2023 / 2024 - absolut | AI5: Veränderung 2023 / 2024 - in Prozent
A6: Träger-Nr. (2024) | B6: Träger-Nr. (2023) | C6: Trägername | D6: Träger- schaft | E6: Vergleichs- typ | F6: Bundes-land-Nr. | G6: Bundesland | H6: Hinweis / Fußnote | J6: Termin der Änderung | K6: Verwaltungskosten | L6: Eingliederungsleistungen | M6: Bürgergeld (ohne Altfälle) | N6: Kosten der Unterkunft | O6: Abweichend zu erbringende Leistungen | P6: Ausgaben für Leistungen zur Sozialversicherung | Q6: Bildung und Teilhabe | R6: Insgesamt (ohne B&T) | S6: Verwaltungskosten | T6: Eingliederungsleistungen | U6: Bürgergeld (ohne Altfälle) | V6: Kosten der Unterkunft | W6: Abweichend zu erbringende Leistungen | X6: Ausgaben für Leistungen zur Sozialversicherung | Y6: Bildung und Teilhabe | Z6: Insgesamt (ohne B&T) | AA6: Verwaltungskosten | AB6: Eingliederungsleistungen | AC6: Bürgergeld (ohne Altfälle) | AD6: Kosten der Unterkunft | AE6: Abweichend zu erbringende Leistungen | AF6: Ausgaben für Leistungen zur Sozialversicherung | AG6: Bildung und Teilhabe | AH6: Insgesamt (ohne B&T) | AI6: Verwaltungskosten | AJ6: Eingliederungsleistungen | AK6: Bürgergeld (ohne Altfälle) | AL6: Kosten der Unterkunft | AM6: Abweichend zu erbringende Leistungen | AN6: Ausgaben für Leistungen zur Sozialversicherung | AO6: Bildung und Teilhabe | AP6: Insgesamt (ohne B&T)
A7: D | B7: D | C7: Deutschland | D7: - | E7: - | F7: D | G7: Deutschland | K7: 6.4482995e+09 | L7: 3.6835652e+09 | M7: 2.2057313e+10 | N7: 1.7474337e+10 | O7: 2.6115767e+08 | P7: 7.1652477e+09 | Q7: X | R7: 5.708992e+10 | S7: 6.139999e+09 | T7: 3.8131858e+09 | U7: 1.913887e+10 | V7: 1.6520604e+10 | W7: 2.9979254e+08 | X7: 6.686731e+09 | Y7: X | Z7: 5.2599183e+10 | AA7: 3.0830053e+08 | AB7: -1.2962056e+08 | AC7: 2.9184427e+09 | AD7: 9.5373295e+08 | AE7: -38634869 | AF7: 4.7851671e+08 | AG7: X | AH7: 4.4907374e+09 | AI7: 5.0211822 | AJ7: -3.3992721 | AK7: 15.248772 | AL7: 5.7729907 | AM7: -12.887202 | AN7: 7.156213 | AO7: X | AP7: 8.5376563
A8: W | B8: W | C8: Westdeutschland | D8: - | E8: - | F8: W | G8: Westdeutschland | K8: 4.8514269e+09 | L8: 2.7969838e+09 | M8: 1.6936316e+10 | N8: 1.3642556e+10 | O8: 1.9454309e+08 | P8: 5.5042137e+09 | Q8: X | R8: 4.392604e+10 | S8: 4.5708721e+09 | T8: 2.8722881e+09 | U8: 1.4652038e+10 | V8: 1.2841436e+10 | W8: 2.2312821e+08 | X8: 5.1293996e+09 | Y8: X | Z8: 4.0289163e+10 | AA8: 2.8055485e+08 | AB8: -75304360 | AC8: 2.284278e+09 | AD8: 8.0111934e+08 | AE8: -28585117 | AF8: 3.7481414e+08 | AG8: X | AH8: 3.6368768e+09 | AI8: 6.1378845 | AJ8: -2.6217551 | AK8: 15.590172 | AL8: 6.2385492 | AM8: -12.811073 | AN8: 7.3071738 | AO8: X | AP8: 9.0269357
A9: O | B9: O | C9: Ostdeutschland | D9: - | E9: - | F9: O | G9: Ostdeutschland | K9: 1.5968726e+09 | L9: 8.8658143e+08 | M9: 5.1209971e+09 | N9: 3.8317814e+09 | O9: 66614581 | P9: 1.6607843e+09 | Q9: X | R9: 1.3163631e+10 | S9: 1.5691269e+09 | T9: 9.4089763e+08 | U9: 4.4868317e+09 | V9: 3.6791678e+09 | W9: 76664333 | X9: 1.5573314e+09 | Y9: X | Z9: 1.231002e+10 | AA9: 27745682 | AB9: -54316198 | AC9: 6.3416543e+08 | AD9: 1.5261361e+08 | AE9: -10049752 | AF9: 1.0345297e+08 | AG9: X | AH9: 8.5361175e+08 | AI9: 1.7682242 | AJ9: -5.7728064 | AK9: 14.133925 | AL9: 4.1480471 | AM9: -13.108771 | AN9: 6.6429647 | AO9: X | AP9: 6.9342842
A10: 01 | B10: 01 | C10: Schleswig-Holstein | D10: - | E10: - | F10: 01 | G10: Schleswig-Holstein | K10: 2.3318588e+08 | L10: 1.2317052e+08 | M10: 7.5816658e+08 | N10: 6.1669803e+08 | O10: 7703793.3 | P10: 2.5403216e+08 | Q10: X | R10: 1.992957e+09 | S10: 2.252194e+08 | T10: 1.3480485e+08 | U10: 6.5268986e+08 | V10: 5.8113117e+08 | W10: 8220452.1 | X10: 2.3769479e+08 | Y10: X | Z10: 1.8397605e+09 | AA10: 7966480.9 | AB10: -11634333 | AC10: 1.0547672e+08 | AD10: 35566866 | AE10: -516658.83 | AF10: 16337368 | AG10: X | AH10: 1.5319644e+08 | AI10: 3.5372091 | AJ10: -8.6305001 | AK10: 16.160312 | AL10: 6.1202819 | AM10: -6.2850416 | AN10: 6.8732546 | AO10: X | AP10: 8.3269774
A11: 02 | B11: 02 | C11: Hamburg | D11: - | E11: - | F11: 02 | G11: Hamburg | K11: 1.9823893e+08 | L11: 1.5194415e+08 | M11: 7.6029079e+08 | N11: 8.5394905e+08 | O11: 8170745.2 | P11: 2.4685997e+08 | Q11: X | R11: 2.2194536e+09 | S11: 1.8463347e+08 | T11: 1.7592508e+08 | U11: 6.5927794e+08 | V11: 757451424 | W11: 9924418.2 | X11: 2.3275562e+08 | Y11: X | Z11: 2.019968e+09 | AA11: 13605467 | AB11: -23980938 | AC11: 1.0101284e+08 | AD11: 96497622 | AE11: -1753673.1 | AF11: 14104357 | AG11: X | AH11: 1.9948568e+08 | AI11: 7.3689063 | AJ11: -13.631335 | AK11: 15.321739 | AL11: 12.739777 | AM11: -17.670286 | AN11: 6.059728 | AO11: X | AP11: 9.8756854
A12: 03 | B12: 03 | C12: Niedersachsen | D12: - | E12: - | F12: 03 | G12: Niedersachsen | K12: 6.3524431e+08 | L12: 3.3759138e+08 | M12: 2.103907e+09 | N12: 1.6311256e+09 | O12: 22282760 | P12: 6.895851e+08 | Q12: X | R12: 5.4197362e+09 | S12: 6.0229752e+08 | T12: 3.4957972e+08 | U12: 1.8639264e+09 | V12: 1.5843777e+09 | W12: 29838491 | X12: 6.5630989e+08 | Y12: X | Z12: 5.0863297e+09 | AA12: 32946791 | AB12: -11988339 | AC12: 2.3998062e+08 | AD12: 46747935 | AE12: -7555731.2 | AF12: 33275217 | AG12: X | AH12: 3.3340649e+08 | AI12: 5.4701854 | AJ12: -3.4293578 | AK12: 12.875005 | AL12: 2.950555 | AM12: -25.322096 | AN12: 5.0700465 | AO12: X | AP12: 6.5549525
A13: 04 | B13: 04 | C13: Bremen | D13: - | E13: - | F13: 04 | G13: Bremen | K13: 1.032326e+08 | L13: 80920806 | M13: 3.8674713e+08 | N13: 3.0300354e+08 | O13: 5360530.6 | P13: 1.2249299e+08 | Q13: X | R13: 1.0017576e+09 | S13: 1.0157149e+08 | T13: 86519447 | U13: 3.3364791e+08 | V13: 2.8989621e+08 | W13: 5551460.8 | X13: 1.1484173e+08 | Y13: X | Z13: 9.3202825e+08 | AA13: 1661112.1 | AB13: -5598641.3 | AC13: 53099219 | AD13: 13107329 | AE13: -190930.17 | AF13: 7651257.3 | AG13: X | AH13: 69729346 | AI13: 1.6354119 | AJ13: -6.4709629 | AK13: 15.914746 | AL13: 4.521387 | AM13: -3.439278 | AN13: 6.6624363 | AO13: X | AP13: 7.4814628
A14: 05 | B14: 05 | C14: Nordrhein-Westfalen | D14: - | E14: - | F14: 05 | G14: Nordrhein-Westfalen | K14: 1.7527622e+09 | L14: 1.1727391e+09 | M14: 6.38929e+09 | N14: 4.8839967e+09 | O14: 70703407 | P14: 2.0318916e+09 | Q14: X | R14: 1.6301383e+10 | S14: 1.658063e+09 | T14: 1.2225217e+09 | U14: 5.5449711e+09 | V14: 4.6250265e+09 | W14: 79519221 | X14: 1.9011503e+09 | Y14: X | Z14: 1.5031252e+10 | AA14: 94699215 | AB14: -49782642 | AC14: 8.4431887e+08 | AD14: 2.5897027e+08 | AE14: -8815813.5 | AF14: 1.3074132e+08 | AG14: X | AH14: 1.2701312e+09 | AI14: 5.7114364 | AJ14: -4.0721275 | AK14: 15.22675 | AL14: 5.5993251 | AM14: -11.086393 | AN14: 6.876959 | AO14: X | AP14: 8.4499364
A15: 06 | B15: 06 | C15: Hessen | D15: - | E15: - | F15: 06 | G15: Hessen | K15: 4.8154224e+08 | L15: 2.2169137e+08 | M15: 1.6029478e+09 | N15: 1.419614e+09 | O15: 22398623 | P15: 5.2769935e+08 | Q15: X | R15: 4.2758934e+09 | S15: 4.5332077e+08 | T15: 2.2901873e+08 | U15: 1.3738759e+09 | V15: 1.3222757e+09 | W15: 24142825 | X15: 4.902985e+08 | Y15: X | Z15: 3.8929325e+09 | AA15: 28221466 | AB15: -7327365.7 | AC15: 2.2907191e+08 | AD15: 97338318 | AE15: -1744201.8 | AF15: 37400853 | AG15: X | AH15: 3.8296098e+08 | AI15: 6.2254958 | AJ15: -3.1994613 | AK15: 16.673406 | AL15: 7.3614237 | AM15: -7.2245143 | AN15: 7.6281802 | AO15: X | AP15: 9.8373394
A16: 07 | B16: 07 | C16: Rheinland-Pfalz | D16: - | E16: - | F16: 07 | G16: Rheinland-Pfalz | K16: 2.5658537e+08 | L16: 1.2340632e+08 | M16: 8.8660923e+08 | N16: 6.4972071e+08 | O16: 8094916.3 | P16: 2.9025144e+08 | Q16: X | R16: 2.214668e+09 | S16: 2.4068156e+08 | T16: 1.268868e+08 | U16: 7.5844471e+08 | V16: 6.0797883e+08 | W16: 8616296.5 | X16: 2.6701011e+08 | Y16: X | Z16: 2.0096183e+09 | AA16: 15903815 | AB16: -3480482 | AC16: 1.2816451e+08 | AD16: 41741884 | AE16: -521380.16 | AF16: 23241330 | AG16: X | AH16: 2.0504968e+08 | AI16: 6.6078246 | AJ16: -2.7429819 | AK16: 16.898333 | AL16: 6.8656805 | AM16: -6.0510935 | AN16: 8.7042883 | AO16: X | AP16: 10.203414
A17: 08 | B17: 08 | C17: Baden-Württemberg | D17: - | E17: - | F17: 08 | G17: Baden-Württemberg | K17: 5.4408124e+08 | L17: 2.9385662e+08 | M17: 1.9391078e+09 | N17: 1.6447576e+09 | O17: 21847516 | P17: 6.3990268e+08 | Q17: X | R17: 5.0835535e+09 | S17: 4.9894702e+08 | T17: 2.762227e+08 | U17: 1.66673e+09 | V17: 1.5290129e+09 | W17: 25916878 | X17: 5.8626998e+08 | Y17: X | Z17: 4.5830995e+09 | AA17: 45134222 | AB17: 17633925 | AC17: 2.7237782e+08 | AD17: 1.1574471e+08 | AE17: -4069362.6 | AF17: 53632700 | AG17: X | AH17: 5.0045401e+08 | AI17: 9.0458947 | AJ17: 6.3839522 | AK17: 16.342048 | AL17: 7.5698976 | AM17: -15.701593 | AN17: 9.1481233 | AO17: X | AP17: 10.919554
A18: 09 | B18: 09 | C18: Bayern | D18: - | E18: - | F18: 09 | G18: Bayern | K18: 5.5203433e+08 | L18: 2.341262e+08 | M18: 1.7753399e+09 | N18: 1.3935529e+09 | O18: 24320913 | P18: 5.9508966e+08 | Q18: X | R18: 4.574464e+09 | S18: 5.1431038e+08 | T18: 2.1210954e+08 | U18: 1.5122063e+09 | V18: 1.3142515e+09 | W18: 27456011 | X18: 5.4406979e+08 | Y18: X | Z18: 4.1244035e+09 | AA18: 37723955 | AB18: 22016658 | AC18: 2.6313361e+08 | AD18: 79301451 | AE18: -3135098.2 | AF18: 51019871 | AG18: X | AH18: 4.5006045e+08 | AI18: 7.3348616 | AJ18: 10.379852 | AK18: 17.400642 | AL18: 6.0339633 | AM18: -11.418622 | AN18: 9.3774497 | AO18: X | AP18: 10.912134
... A25: 16 | B25: 16 | C25: Thüringen | D25: - | E25: - | F25: 16 | G25: Thüringen | K25: 1.6236192e+08 | L25: 64205636 | M25: 4.8771278e+08 | N25: 2.957966e+08 | O25: 6878601.8 | P25: 1.5744493e+08 | Q25: X | R25: 1.1744005e+09 | S25: 1.5823893e+08 | T25: 67828049 | U25: 4.3581457e+08 | V25: 2.8392627e+08 | W25: 8648642.3 | X25: 1.4858019e+08 | Y25: X | Z25: 1.1030367e+09 | AA25: 4122989.9 | AB25: -3622413.2 | AC25: 51898202 | AD25: 11870332 | AE25: -1770040.5 | AF25: 8864742.4 | AG25: X | AH25: 71363813 | AI25: 2.605547 | AJ25: -5.3405829 | AK25: 11.908322 | AL25: 4.1807798 | AM25: -20.466109 | AN25: 5.9663018 | AO25: X | AP25: 6.469759
A26: 03002 | C26: JC Vorpommern-Greifswald | D26: gE | E26: IIId | F26: 13 | G26: Mecklenburg-Vorpommern | K26: 25300148 | L26: 12585733 | M26: 73434908 | N26: 45391276 | O26: 1023801.2 | P26: 23870983 | Q26: 2276910.6 | R26: 1.8160685e+08 | S26: 23992422 | T26: 15332277 | U26: 64621571 | V26: 45629288 | W26: 1024665.2 | X26: 22551202 | Y26: 2210816.2 | Z26: 1.7315142e+08 | AA26: 1307725.6 | AB26: -2746544 | AC26: 8813337 | AD26: -238011.44 | AE26: -863.98 | AF26: 1319781 | AG26: 66094.46 | AH26: 8455424.2 | AI26: 5.4505777 | AJ26: -17.913478 | AK26: 13.638382 | AL26: -0.52161989 | AM26: -0.084318274 | AN26: 5.8523755 | AO26: 2.9895955 | AP26: 4.8832542
A27: 03102 | C27: JC Mecklenburgische Seenplatte Süd | D27: gE | E27: IIId | F27: 13 | G27: Mecklenburg-Vorpommern | K27: 17339875 | L27: 7073905.6 | M27: 50412561 | N27: 31117423 | O27: 858317.28 | P27: 16241827 | Q27: 1775195.9 | R27: 1.2304391e+08 | S27: 16539620 | T27: 6492249 | U27: 43752351 | V27: 29558971 | W27: 874281.11 | X27: 15055669 | Y27: 1549998.4 | Z27: 1.1227314e+08 | AA27: 800255.27 | AB27: 581656.59 | AC27: 6660210.2 | AD27: 1558452.6 | AE27: -15963.83 | AF27: 1186157.7 | AG27: 225197.53 | AH27: 10770769 | AI27: 4.838414 | AJ27: 8.9592464 | AK27: 15.22252 | AL27: 5.2723507 | AM27: -1.8259379 | AN27: 7.8784789 | AO27: 14.528888 | AP27: 9.5933618
A28: 03122 | C28: JC Mecklenburgische Seenplatte Nord | D28: gE | E28: IIId | F28: 13 | G28: Mecklenburg-Vorpommern | K28: 12866847 | L28: 4007727 | M28: 32101052 | N28: 19767628 | O28: 464567.08 | P28: 10390224 | Q28: 932499.98 | R28: 79598044 | S28: 13148430 | T28: 4658640 | U28: 28591251 | V28: 19529064 | W28: 397953.44 | X28: 10096489 | Y28: 904267.97 | Z28: 76421828 | AA28: -281583.5 | AB28: -650913.08 | AC28: 3509800.4 | AD28: 238563.67 | AE28: 66613.64 | AF28: 293734.67 | AG28: 28232.01 | AH28: 3176215.8 | AI28: -2.141575 | AJ28: -13.972169 | AK28: 12.275785 | AL28: 1.2215827 | AM28: 16.739054 | AN28: 2.9092754 | AO28: 3.1220845 | AP28: 4.1561631
A29: 03202 | C29: JC Rostock, Hansestadt | D29: gE | E29: IIIe | F29: 13 | G29: Mecklenburg-Vorpommern | K29: 22567061 | L29: 9931609.6 | M29: 64311827 | N29: 45230145 | O29: 998142.2 | P29: 21574233 | Q29: 768130.98 | R29: 1.6461302e+08 | S29: 22678138 | T29: 11041181 | U29: 56513808 | V29: 43657663 | W29: 1138693.1 | X29: 20352233 | Y29: 745464.77 | Z29: 1.5538172e+08 | AA29: -111076.83 | AB29: -1109571.6 | AC29: 7798018.9 | AD29: 1572481.9 | AE29: -140550.87 | AF29: 1222000.8 | AG29: 22666.21 | AH29: 9231302.2 | AI29: -0.48979696 | AJ29: -10.049392 | AK29: 13.798431 | AL29: 3.6018461 | AM29: -12.343174 | AN29: 6.004259 | AO29: 3.0405474 | AP29: 5.9410479
A30: 03208 | C30: JC Landkreis Rostock | D30: gE | E30: IIIa | F30: 13 | G30: Mecklenburg-Vorpommern | K30: 15117537 | L30: 8058731.3 | M30: 48224427 | N30: 31607849 | O30: 539498.75 | P30: 15334952 | Q30: 1581754 | R30: 1.18883e+08 | S30: 15272343 | T30: 7027011.2 | U30: 42662715 | V30: 30313280 | W30: 655520.16 | X30: 14502805 | Y30: 1394189.5 | Z30: 1.1043367e+08 | AA30: -154805.34 | AB30: 1031720.2 | AC30: 5561711.6 | AD30: 1294569 | AE30: -116021.41 | AF30: 832147.43 | AG30: 187564.55 | AH30: 8449321.4 | AI30: -1.0136319 | AJ30: 14.682205 | AK30: 13.036469 | AL30: 4.2706331 | AM30: -17.699137 | AN30: 5.737838 | AO30: 13.453304 | AP30: 7.6510371
A31: 03302 | C31: JC Schwerin, Landeshauptstadt | D31: gE | E31: IIIe | F31: 13 | G31: Mecklenburg-Vorpommern | K31: 13145604 | L31: 7746878.9 | M31: 44877132 | N31: 28679218 | O31: 1158691.5 | P31: 14314467 | Q31: 1989494.8 | R31: 1.0992199e+08 | S31: 12960597 | T31: 7765231.6 | U31: 38686342 | V31: 26280256 | W31: 1188879.4 | X31: 13325211 | Y31: 1847875.5 | Z31: 1.0020652e+08 | AA31: 185006.68 | AB31: -18352.73 | AC31: 6190789.7 | AD31: 2398961.6 | AE31: -30187.91 | AF31: 989256.32 | AG31: 141619.31 | AH31: 9715473.6 | AI31: 1.4274549 | AJ31: -0.23634491 | AK31: 16.00252 | AL31: 9.1283798 | AM31: -2.5391902 | AN31: 7.423945 | AO31: 7.6638989 | AP31: 9.6954508
A32: 03304 | C32: JC Nordwestmecklenburg | D32: gE | E32: IIIa | F32: 13 | G32: Mecklenburg-Vorpommern | K32: 12398500 | L32: 5892383.4 | M32: 36695688 | N32: 22717096 | O32: 305675.52 | P32: 11957198 | Q32: 407111.45 | R32: 89966541 | S32: 12052213 | T32: 5514736.4 | U32: 32407250 | V32: 22617452 | W32: 455136.46 | X32: 11459009 | Y32: 432172.64 | Z32: 84505797 | AA32: 346287.42 | AB32: 377646.98 | AC32: 4288437.8 | AD32: 99643.44 | AE32: -149460.94 | AF32: 498189.15 | AG32: -25061.19 | AH32: 5460743.9 | AI32: 2.8732269 | AJ32: 6.8479607 | AK32: 13.232958 | AL32: 0.44055997 | AM32: -32.83871 | AN32: 4.3475762 | AO32: -5.798884 | AP32: 6.4619755
A33: 03324 | C33: JC Ludwigslust-Parchim | D33: gE | E33: IIId | F33: 13 | G33: Mecklenburg-Vorpommern | K33: 14990419 | L33: 7394498.3 | M33: 46079781 | N33: 26435416 | O33: 684633.98 | P33: 14356149 | Q33: 1553636.5 | R33: 1.099409e+08 | S33: 14687780 | T33: 8135660.3 | U33: 40796687 | V33: 26252620 | W33: 478106.36 | X33: 13810860 | Y33: 1367918.4 | Z33: 1.0416171e+08 | AA33: 302639.2 | AB33: -741161.93 | AC33: 5283093.3 | AD33: 182796.3 | AE33: 206527.62 | AF33: 545288.87 | AG33: 185718.17 | AH33: 5779183.3 | AI33: 2.0604829 | AJ33: -9.1100403 | AK33: 12.949809 | AL33: 0.69629736 | AM33: 43.197003 | AN33: 3.9482614 | AO33: 13.5767 | AP33: 5.5482798
A34: 03444 | C34: JC Vorpommern-Rügen | D34: zkT | E34: IIId | F34: 13 | G34: Mecklenburg-Vorpommern | K34: . | L34: 11464732 | M34: 65200239 | N34: 43275418 | O34: 1080477 | P34: 21515054 | Q34: 453355 | R34: . | S34: 20147936 | T34: 11617158 | U34: 58234951 | V34: 41361501 | W34: 972951 | X34: 19889354 | Y34: 418004 | Z34: 152223851 | AA34: X | AB34: -152426 | AC34: 6965288 | AD34: 1913917 | AE34: 107526 | AF34: 1625700 | AG34: 35351 | AH34: X | AI34: X | AJ34: -1.3120765 | AK34: 11.960666 | AL34: 4.627291 | AM34: 11.051533 | AN34: 8.1737195 | AO34: 8.4570961 | AP34: X
A35: 03502 | C35: JC Cottbus, Stadt | D35: gE | E35: IIIe | F35: 12 | G35: Brandenburg | K35: 12788882 | L35: 6904215.3 | M35: 39389676 | N35: 25056525 | O35: 627507.56 | P35: 12814034 | Q35: 2041326.8 | R35: 97580839 | S35: 12318260 | T35: 8251069.6 | U35: 35244069 | V35: 25078186 | W35: 834006.79 | X35: 12161631 | Y35: 1951848.1 | Z35: 93887222 | AA35: 470621.91 | AB35: -1346854.4 | AC35: 4145607.4 | AD35: -21660.56 | AE35: -206499.23 | AF35: 652402.55 | AG35: 89478.69 | AH35: 3693617.7 | AI35: 3.8205227 | AJ35: -16.323391 | AK35: 11.762568 | AL35: -0.086372117 | AM35: -24.759898 | AN35: 5.364433 | AO35: 4.5843059 | AP35: 3.9341006
A36: 03504 | C36: JC Elbe-Elster | D36: gE | E36: IIId | F36: 12 | G36: Brandenburg | K36: 8779904.7 | L36: 3608379.7 | M36: 24732204 | N36: 15742993 | O36: 320022.77 | P36: 7964689.6 | Q36: 560948.77 | R36: 61148195 | S36: 9012191.6 | T36: 3933749.9 | U36: 22023515 | V36: 15790500 | W36: 449843.7 | X36: 7598315.3 | Y36: 515942.97 | Z36: 58808115 | AA36: -232286.93 | AB36: -325370.25 | AC36: 2708689.7 | AD36: -47506.21 | AE36: -129820.93 | AF36: 366374.31 | AG36: 45005.8 | AH36: 2340079.7 | AI36: -2.5774744 | AJ36: -8.271249 | AK36: 12.29908 | AL36: -0.30085311 | AM36: -28.859119 | AN36: 4.8217835 | AO36: 8.7230184 | AP36: 3.9791782
A37: 03506 | C37: JC Oberspreewald-Lausitz | D37: gE | E37: IIId | F37: 12 | G37: Brandenburg | K37: 11431408 | L37: 4200927.2 | M37: 30504896 | N37: 19540024 | O37: 253086.55 | P37: 9912761.2 | Q37: 749214.95 | R37: 75843103 | S37: 11758653 | T37: 4467777.3 | U37: 26983495 | V37: 20104389 | W37: 222674.97 | X37: 9450680.7 | Y37: 739224.72 | Z37: 72987670 | AA37: -327245.06 | AB37: -266850.04 | AC37: 3521400.8 | AD37: -564364.62 | AE37: 30411.58 | AF37: 462080.48 | AG37: 9990.23 | AH37: 2855433.1 | AI37: -2.7830148 | AJ37: -5.9727695 | AK37: 13.050202 | AL37: -2.8071713 | AM37: 13.657386 | AN37: 4.8893883 | AO37: 1.351447 | AP37: 3.912213
A38: 03510 | C38: JC Dahme-Spreewald | D38: gE | E38: IIIe | F38: 12 | G38: Brandenburg | K38: 10049015 | L38: 3851995.1 | M38: 28496916 | N38: 21550454 | O38: 352567.84 | P38: 9445266.4 | Q38: 927830.63 | R38: 73746213 | S38: 9628385.1 | T38: 4462035.5 | U38: 24988024 | V38: 21011842 | W38: 305649.56 | X38: 8976710.4 | Y38: 834370.45 | Z38: 69372647 | AA38: 420629.5 | AB38: -610040.37 | AC38: 3508891.4 | AD38: 538611.44 | AE38: 46918.28 | AF38: 468556.02 | AG38: 93460.18 | AH38: 4373566.3 | AI38: 4.3686402 | AJ38: -13.671796 | AK38: 14.042293 | AL38: 2.5633708 | AM38: 15.350351 | AN38: 5.2196852 | AO38: 11.201281 | AP38: 6.3044536
A39: 03538 | C39: JC Spree-Neiße | D39: zkT | E39: IIIa | F39: 12 | G39: Brandenburg | K39: 10239195 | L39: 3747302 | M39: 27233724 | N39: 16555343 | O39: 194379 | P39: 8443353 | Q39: 1360261 | R39: 66413296 | S39: 10137973 | T39: 4321045 | U39: 25232091 | V39: 17052281 | W39: 321754 | X39: 8283698 | Y39: 1255087 | Z39: 65348842 | AA39: 101222 | AB39: -573743 | AC39: 2001633 | AD39: -496938 | AE39: -127375 | AF39: 159655 | AG39: 105174 | AH39: 1064454 | AI39: 0.99844417 | AJ39: -13.277876 | AK39: 7.9328859 | AL39: -2.9142025 | AM39: -39.587697 | AN39: 1.9273397 | AO39: 8.3798175 | AP39: 1.6288797
A40: 03602 | C40: JC Barnim | D40: gE | E40: IIIa | F40: 12 | G40: Brandenburg | K40: 13377554 | L40: 5500206.1 | M40: 39032063 | N40: 25879497 | O40: 272457.93 | P40: 12710487 | Q40: 961819.46 | R40: 96772264 | S40: 13177531 | T40: 6381465.5 | U40: 34801212 | V40: 25280447 | W40: 374345.61 | X40: 12176806 | Y40: 936938.5 | Z40: 92191807 | AA40: 200023.19 | AB40: -881259.44 | AC40: 4230850.8 | AD40: 599049.96 | AE40: -101887.68 | AF40: 533680.47 | AG40: 24880.96 | AH40: 4580457.3 | AI40: 1.517911 | AJ40: -13.809672 | AK40: 12.157194 | AL40: 2.3696178 | AM40: -27.217544 | AN40: 4.3827623 | AO40: 2.6555596 | AP40: 4.9683996
A41: 03604 | C41: JC Uckermark | D41: zkT | E41: IIId | F41: 12 | G41: Brandenburg | K41: 15260617 | L41: 9342258 | M41: 48170046 | N41: 31331952 | O41: 576045 | P41: 15512338 | Q41: 1388454 | R41: 120193256 | S41: 15002331 | T41: 10594986 | U41: 41032699 | V41: 30020359 | W41: 542535 | X41: 14344581 | Y41: 1306894 | Z41: 111537491 | AA41: 258286 | AB41: -1252728 | AC41: 7137347 | AD41: 1311593 | AE41: 33510 | AF41: 1167757 | AG41: 81560 | AH41: 8655765 | AI41: 1.7216391 | AJ41: -11.823782 | AK41: 17.394291 | AL41: 4.3690117 | AM41: 6.17656 | AN41: 8.1407536 | AO41: 6.240751 | AP41: 7.7604086
A42: 03702 | C42: JC Frankfurt (Oder), Stadt | D42: gE | E42: IIIe | F42: 12 | G42: Brandenburg | K42: 8600673.8 | L42: 2976471.5 | M42: 22583275 | N42: 16157496 | O42: 561169.11 | P42: 7397098.5 | Q42: 850844.63 | R42: 58276184 | S42: 8324439.3 | T42: 3424689.8 | U42: 19928148 | V42: 15784953 | W42: 590226.05 | X42: 7108599.9 | Y42: 787266.59 | Z42: 55161056 | AA42: 276234.56 | AB42: -448218.33 | AC42: 2655127.2 | AD42: 372543.27 | AE42: -29056.94 | AF42: 288498.62 | AG42: 63578.04 | AH42: 3115128.3 | AI42: 3.3183564 | AJ42: -13.087852 | AK42: 13.323502 | AL42: 2.3601164 | AM42: -4.9230189 | AN42: 4.058445 | AO42: 8.0757955 | AP42: 5.6473327
A43: 03706 | C43: JC Oder-Spree | D43: zkT | E43: IIIa | F43: 12 | G43: Brandenburg | K43: 15333119 | L43: 5511167 | M43: 47576138 | N43: 30409567 | O43: 412187 | P43: 14421004 | Q43: 1620931 | R43: 113663182 | S43: 14638093 | T43: 5920528 | U43: 41848711 | V43: 29194462 | W43: 491494 | X43: 13618605 | Y43: 1368296 | Z43: 105711893 | AA43: 695026 | AB43: -409361 | AC43: 5727427 | AD43: 1215105 | AE43: -79307 | AF43: 802399 | AG43: 252635 | AH43: 7951289 | AI43: 4.7480638 | AJ43: -6.9142651 | AK43: 13.68603 | AL43: 4.1621079 | AM43: -16.135904 | AN43: 5.8919324 | AO43: 18.463476 | AP43: 7.5216598
A44: 03708 | C44: JC Märkisch-Oderland | D44: gE | E44: IIIa | F44: 12 | G44: Brandenburg | K44: 14433021 | L44: 5471924.8 | M44: 40562851 | N44: 24748942 | O44: 540051.27 | P44: 13029528 | Q44: 1536435.9 | R44: 98786319 | S44: 14496370 | T44: 6522033.6 | U44: 35932326 | V44: 23985085 | W44: 659553.92 | X44: 12416178 | Y44: 1389806.2 | Z44: 94011547 | AA44: -63348.77 | AB44: -1050108.8 | AC44: 4630525 | AD44: 763856.74 | AE44: -119502.65 | AF44: 613350.44 | AG44: 146629.63 | AH44: 4774772 | AI44: -0.43699746 | AJ44: -16.100941 | AK44: 12.886795 | AL44: 3.1847155 | AM44: -18.118708 | AN44: 4.9399295 | AO44: 10.550365 | AP44: 5.0789208
A45: 03802 | C45: JC Ostprignitz-Ruppin | D45: zkT | E45: IIId | F45: 12 | G45: Brandenburg | K45: 10510741 | L45: 3241152 | M45: 25958257 | N45: 16574508 | O45: 230745 | P45: 8406900 | Q45: 746749 | R45: 64922303 | S45: 10146884 | T45: 3172618 | U45: 23771427 | V45: 16392654 | W45: 297737 | X45: 8171057 | Y45: 648175 | Z45: 61952377 | AA45: 363857 | AB45: 68534 | AC45: 2186830 | AD45: 181854 | AE45: -66992 | AF45: 235843 | AG45: 98574 | AH45: 2969926 | AI45: 3.5858989 | AJ45: 2.1601718 | AK45: 9.1994057 | AL45: 1.1093628 | AM45: -22.500395 | AN45: 2.8863218 | AO45: 15.20793 | AP45: 4.7938855
A46: 03804 | C46: JC Prignitz | D46: gE | E46: IIId | F46: 12 | G46: Brandenburg | K46: 7814044.3 | L46: 3307498.7 | M46: 23956023 | N46: 14482766 | O46: 497831.95 | P46: 7505671.9 | Q46: 626717.07 | R46: 57563836 | S46: 7820742.4 | T46: 3421559.2 | U46: 20451912 | V46: 13690776 | W46: 393227.52 | X46: 6974058.6 | Y46: 562600.67 | Z46: 52752276 | AA46: -6698.05 | AB46: -114060.52 | AC46: 3504110.6 | AD46: 791989.41 | AE46: 104604.43 | AF46: 531613.25 | AG46: 64116.4 | AH46: 4811559.1 | AI46: -0.085644683 | AJ46: -3.3335831 | AK46: 17.133413 | AL46: 5.7848393 | AM46: 26.601503 | AN46: 7.6227242 | AO46: 11.396432 | AP46: 9.1210454
A47: 03806 | C47: JC Oberhavel | D47: zkT | E47: IIIa | F47: 12 | G47: Brandenburg | K47: . | L47: 6918539 | M47: 40102971 | N47: 27712658 | O47: 414529 | P47: 13403410 | Q47: 1066068 | R47: . | S47: . | T47: 7085188 | U47: 35981319 | V47: 27307179 | W47: 506109 | X47: 12748809 | Y47: 1036863 | Z47: . | AA47: X | AB47: -166649 | AC47: 4121652 | AD47: 405479 | AE47: -91580 | AF47: 654601 | AG47: 29205 | AH47: X | AI47: X | AJ47: -2.3520759 | AK47: 11.454978 | AL47: 1.4848806 | AM47: -18.094916 | AN47: 5.1346051 | AO47: 2.8166691 | AP47: X
A48: 03846 | C48: JC Havelland | D48: zkT | E48: IIIa | F48: 12 | G48: Brandenburg | K48: 12885874 | L48: 3252531 | M48: 36759117 | N48: 26006744 | O48: 391688 | P48: 10864997 | Q48: 1176911 | R48: 90160951 | S48: 12226997 | T48: 2968387 | U48: . | V48: 24693384 | W48: 72849 | X48: 9978328 | Y48: 909760 | Z48: . | AA48: 658877 | AB48: 284144 | AC48: X | AD48: 1313360 | AE48: 318839 | AF48: 886669 | AG48: 267151 | AH48: X | AI48: 5.3887066 | AJ48: 9.5723368 | AK48: X | AL48: 5.3186716 | AM48: .X | AN48: 8.8859476 | AO48: 29.364997 | AP48: X
A49: 03902 | C49: JC Brandenburg an der Havel, Stadt | D49: gE | E49: IIIe | F49: 12 | G49: Brandenburg | K49: 10635575 | L49: 3965072.1 | M49: 29471602 | N49: 21276353 | O49: 427344.54 | P49: 9645183.6 | Q49: 937423.46 | R49: 75421131 | S49: 10074206 | T49: 3765580.6 | U49: 26039370 | V49: 20619433 | W49: 506797.52 | X49: 9161791.4 | Y49: 971789.01 | Z49: 70167178 | AA49: 561368.69 | AB49: 199491.5 | AC49: 3432232.7 | AD49: 656920.69 | AE49: -79452.98 | AF49: 483392.17 | AG49: -34365.55 | AH49: 5253952.8 | AI49: 5.5723368 | AJ49: 5.297762 | AK49: 13.180936 | AL49: 3.18593 | AM49: -15.67746 | AN49: 5.2761753 | AO49: -3.536318 | AP49: 7.4877642
A50: 03904 | C50: JC Potsdam, Stadt | D50: gE | E50: IIIe | F50: 12 | G50: Brandenburg | K50: 15513271 | L50: 8028251.3 | M50: 48718577 | N50: 37416995 | O50: 593697.04 | P50: 16157019 | Q50: 1461806.1 | R50: 1.2642781e+08 | S50: 15693845 | T50: 7428545.1 | U50: 43063521 | V50: 35328256 | W50: 765202.25 | X50: 15411786 | Y50: 472907.41 | Z50: 1.1769115e+08 | AA50: -180574.13 | AB50: 599706.24 | AC50: 5655055.9 | AD50: 2088739.1 | AE50: -171505.21 | AF50: 745233.49 | AG50: 988898.68 | AH50: 8736655.4 | AI50: -1.1506048 | AJ50: 8.0729973 | AK50: 13.131894 | AL50: 5.9123754 | AM50: -22.413056 | AN50: 4.8354779 | AO50: 209.11042 | AP50: 7.4233747
A51: 03908 | C51: JC Teltow-Fläming | D51: gE | E51: IIIa | F51: 12 | G51: Brandenburg | K51: 11362768 | L51: 3887980.9 | M51: 31779222 | N51: 22878852 | O51: 423293.07 | P51: 10357959 | Q51: 719759.13 | R51: 80690075 | S51: 11056045 | T51: 3633537.8 | U51: 27837079 | V51: 21354335 | W51: 445173.83 | X51: 9725303.9 | Y51: 648607.78 | Z51: 74051475 | AA51: 306723.18 | AB51: 254443.09 | AC51: 3942142.8 | AD51: 1524516.6 | AE51: -21880.76 | AF51: 632655.05 | AG51: 71151.35 | AH51: 6638599.9 | AI51: 2.7742576 | AJ51: 7.0026268 | AK51: 14.161481 | AL51: 7.1391435 | AM51: -4.9151047 | AN51: 6.5052471 | AO51: 10.969858 | AP51: 8.964845
A52: 03942 | C52: JC Potsdam-Mittelmark | D52: zkT | E52: IIIa | F52: 12 | G52: Brandenburg | K52: 10223856 | L52: 3192766 | M52: 26847119 | N52: 20428060 | O52: 230626 | P52: 9654961 | Q52: 815616 | R52: 70577388 | S52: 10023734 | T52: 3208516 | U52: 25044093 | V52: 20117278 | W52: 291166 | X52: 9120744 | Y52: 783751 | Z52: 67805531 | AA52: 200122 | AB52: -15750 | AC52: 1803026 | AD52: 310782 | AE52: -60540 | AF52: 534217 | AG52: 31865 | AH52: 2771857 | AI52: 1.9964816 | AJ52: -0.49088114 | AK52: 7.1994063 | AL52: 1.5448511 | AM52: -20.792263 | AN52: 5.8571647 | AO52: 4.0657045 | AP52: 4.0879512
A53: 04202 | C53: JC Dessau-Roßlau | D53: gE | E53: IIId | F53: 15 | G53: Sachsen-Anhalt | K53: 9608696.8 | L53: 4942752.8 | M53: 29814803 | N53: 19799968 | O53: 553356.25 | P53: 9500567.4 | Q53: 995885.21 | R53: 74220144 | S53: 9013550.4 | T53: 4881456.8 | U53: 26677180 | V53: 19871623 | W53: 667995.43 | X53: 9088074.4 | Y53: 840151.16 | Z53: 70199881 | AA53: 595146.42 | AB53: 61296.04 | AC53: 3137622.3 | AD53: -71655.48 | AE53: -114639.18 | AF53: 412492.94 | AG53: 155734.05 | AH53: 4020263.1 | AI53: 6.6027968 | AJ53: 1.2556915 | AK53: 11.761447 | AL53: -0.36059198 | AM53: -17.161671 | AN53: 4.5388376 | AO53: 18.536432 | AP53: 5.7268802
A54: 04208 | C54: JC Anhalt-Bitterfeld | D54: zkT | E54: IIId | F54: 15 | G54: Sachsen-Anhalt | K54: 15951765 | L54: 9562556 | M54: 48122384 | N54: 28672016 | O54: 306409 | P54: 15354705 | Q54: 1364938 | R54: 117969835 | S54: 15284659 | T54: 9259268 | U54: 42731591 | V54: 29287485 | W54: 369597 | X54: 15020742 | Y54: 1265388 | Z54: 111953342 | AA54: 667106 | AB54: 303288 | AC54: 5390793 | AD54: -615469 | AE54: -63188 | AF54: 333963 | AG54: 99550 | AH54: 6016493 | AI54: 4.3645462 | AJ54: 3.2755073 | AK54: 12.615475 | AL54: -2.1014744 | AM54: -17.096459 | AN54: 2.2233456 | AO54: 7.8671522 | AP54: 5.3741075
A55: 04214 | C55: JC Wittenberg | D55: gE | E55: IIId | F55: 15 | G55: Sachsen-Anhalt | K55: 11198857 | L55: 5059314.4 | M55: 31213983 | N55: 17895496 | O55: 453288.39 | P55: 10102771 | Q55: 857364.88 | R55: 75923709 | S55: 11016139 | T55: 5975903.8 | U55: 28099364 | V55: 18165232 | W55: 493033.22 | X55: 9810865 | Y55: 841013.08 | Z55: 73560537 | AA55: 182718.3 | AB55: -916589.5 | AC55: 3114619 | AD55: -269736.26 | AE55: -39744.83 | AF55: 291906.05 | AG55: 16351.8 | AH55: 2363172.8 | AI55: 1.658642 | AJ55: -15.33809 | AK55: 11.084305 | AL55: -1.484904 | AM55: -8.0612884 | AN55: 2.9753345 | AO55: 1.9442979 | AP55: 3.2125552
A56: 04306 | C56: JC Harz | D56: zkT | E56: IIId | F56: 15 | G56: Sachsen-Anhalt | K56: 18203358 | L56: 10504865 | M56: 55427315 | N56: 33162957 | O56: 310859 | P56: 17947208 | Q56: 2649715 | R56: 135556562 | S56: 16897073 | T56: 11509465 | U56: 51009759 | V56: 34011538 | W56: 417672 | X56: . | Y56: 2262404 | Z56: . | AA56: 1306285 | AB56: -1004600 | AC56: 4417556 | AD56: -848581 | AE56: -106813 | AF56: X | AG56: 387311 | AH56: X | AI56: 7.730836 | AJ56: -8.7284683 | AK56: 8.6602174 | AL56: -2.4949798 | AM56: -25.573416 | AN56: X | AO56: 17.119445 | AP56: X
A57: 04308 | C57: JC Salzlandkreis | D57: zkT | E57: IIId | F57: 15 | G57: Sachsen-Anhalt | K57: 22108966 | L57: 13812298 | M57: 68300111 | N57: 39084229 | O57: 834293 | P57: 21513533 | Q57: 3482414 | R57: 165653430 | S57: 21364373 | T57: 12552737 | U57: 61990966 | V57: 39318763 | W57: 813148 | X57: 20730561 | Y57: 2550088 | Z57: 156770548 | AA57: 744593 | AB57: 1259561 | AC57: 6309145 | AD57: -234534 | AE57: 21145 | AF57: 782972 | AG57: 932326 | AH57: 8882882 | AI57: 3.4852088 | AJ57: 10.034154 | AK57: 10.177523 | AL57: -0.59649384 | AM57: 2.6003876 | AN57: 3.7768973 | AO57: 36.560542 | AP57: 5.6661676
A58: 04402 | C58: JC Halle (Saale), Stadt | D58: gE | E58: IIIe | F58: 15 | G58: Sachsen-Anhalt | K58: 33944790 | L58: 18334186 | M58: 1.0817481e+08 | N58: 66903480 | O58: 1376942.6 | P58: 33900377 | Q58: 3277658.5 | R58: 2.6263459e+08 | S58: 34116674 | T58: 20113021 | U58: 97512874 | V58: 66277467 | W58: 1537661.8 | X58: 32813780 | Y58: 3276688.9 | Z58: 2.5237148e+08 | AA58: -171883.9 | AB58: -1778834.8 | AC58: 10661939 | AD58: 626013.39 | AE58: -160719.12 | AF58: 1086596.9 | AG58: 969.59 | AH58: 10263111 | AI58: -0.50381201 | AJ58: -8.8441952 | AK58: 10.933878 | AL58: 0.94453427 | AM58: -10.452176 | AN58: 3.3114042 | AO58: 0.029590542 | AP58: 4.0666684
A59: 04412 | C59: JC Saalekreis | D59: zkT | E59: IIId | F59: 15 | G59: Sachsen-Anhalt | K59: 14770442 | L59: 7372041 | M59: 46243453 | N59: 28595450 | O59: 740377 | P59: 15556488 | Q59: 1594349 | R59: 113278251 | S59: 14358908 | T59: 8511557 | U59: 40730540 | V59: 27636796 | W59: 800420 | X59: 14748262 | Y59: 1532449 | Z59: 106786483 | AA59: 411534 | AB59: -1139516 | AC59: 5512913 | AD59: 958654 | AE59: -60043 | AF59: 808226 | AG59: 61900 | AH59: 6491768 | AI59: 2.8660536 | AJ59: -13.387868 | AK59: 13.535084 | AL59: 3.4687595 | AM59: -7.5014367 | AN59: 5.480144 | AO59: 4.0392861 | AP59: 6.0792039
A60: 04418 | C60: JC Burgenlandkreis | D60: zkT | E60: IIId | F60: 15 | G60: Sachsen-Anhalt | K60: 18467746 | L60: 10221491 | M60: 58383458 | N60: 34472704 | O60: 517167 | P60: 19210695 | Q60: 1782876 | R60: 141273261 | S60: 18097169 | T60: 9523864 | U60: 52752770 | V60: 34231863 | W60: 881379 | X60: 18112580 | Y60: 1621326 | Z60: 133599625 | AA60: 370577 | AB60: 697627 | AC60: 5630688 | AD60: 240841 | AE60: -364212 | AF60: 1098115 | AG60: 161550 | AH60: 7673636 | AI60: 2.047707 | AJ60: 7.3250416 | AK60: 10.67373 | AL60: 0.70355797 | AM60: -41.322972 | AN60: 6.0627199 | AO60: 9.9640664 | AP60: 5.7437556
A61: 04448 | C61: JC Mansfeld-Südharz | D61: gE | E61: IIId | F61: 15 | G61: Sachsen-Anhalt | K61: 17026476 | L61: 7034418 | M61: 47476541 | N61: 30469735 | O61: 640420.49 | P61: 14905919 | Q61: 1538427.7 | R61: 1.1755351e+08 | S61: 16966730 | T61: 7564880.2 | U61: 42531731 | V61: 29632074 | W61: 604749.85 | X61: 14271227 | Y61: 1321076.2 | Z61: 1.1157139e+08 | AA61: 59746.64 | AB61: -530462.19 | AC61: 4944810.6 | AD61: 837661.35 | AE61: 35670.64 | AF61: 634692.01 | AG61: 217351.51 | AH61: 5982119.1 | AI61: 0.35213999 | AJ61: -7.0121691 | AK61: 11.626168 | AL61: 2.8268739 | AM61: 5.8984124 | AN61: 4.4473542 | AO61: 16.45261 | AP61: 5.3616962
A62: 04502 | C62: JC Magdeburg, Landeshauptstadt | D62: gE | E62: IIIe | F62: 15 | G62: Sachsen-Anhalt | K62: 31204315 | L62: 17392557 | M62: 95518665 | N62: 62794933 | O62: 893349.47 | P62: 30403315 | Q62: 734348.6 | R62: 2.3820713e+08 | S62: 29538273 | T62: 19974257 | U62: 85807448 | V62: 62144717 | W62: 1069105.4 | X62: 29496844 | Y62: 697947.95 | Z62: 2.2803064e+08 | AA62: 1666042.2 | AB62: -2581700.4 | AC62: 9711216.4 | AD62: 650215.82 | AE62: -175755.97 | AF62: 906470.86 | AG62: 36400.65 | AH62: 10176489 | AI62: 5.6402831 | AJ62: -12.925139 | AK62: 11.317452 | AL62: 1.046293 | AM62: -16.439536 | AN62: 3.0731114 | AO62: 5.2153817 | AP62: 4.4627725
A63: 04506 | C63: JC Jerichower Land | D63: gE | E63: IIId | F63: 15 | G63: Sachsen-Anhalt | K63: 8013218.1 | L63: 3120201.2 | M63: 23215376 | N63: 13892102 | O63: 227954.47 | P63: 7152597.9 | Q63: 638554.22 | R63: 55621450 | S63: 8082356 | T63: 3500575.2 | U63: 20888342 | V63: 14049671 | W63: 238229.58 | X63: 7064166.4 | Y63: 590391.67 | Z63: 53823340 | AA63: -69137.88 | AB63: -380373.94 | AC63: 2327033.9 | AD63: -157568.61 | AE63: -10275.11 | AF63: 88431.5 | AG63: 48162.55 | AH63: 1798109.8 | AI63: -0.85541741 | AJ63: -10.866041 | AK63: 11.140347 | AL63: -1.121511 | AM63: -4.3131126 | AN63: 1.2518321 | AO63: 8.1577286 | AP63: 3.3407622
A64: 04514 | C64: JC Börde | D64: gE | E64: IIId | F64: 15 | G64: Sachsen-Anhalt | K64: 11625529 | L64: 5409577.6 | M64: 33906139 | N64: 19739366 | O64: 374949.64 | P64: 10933879 | Q64: 763437.69 | R64: 81989440 | S64: 11710222 | T64: 5860125.1 | U64: 30518118 | V64: 20422726 | W64: 422928.51 | X64: 10576303 | Y64: 747248.49 | Z64: 79510422 | AA64: -84693.03 | AB64: -450547.45 | AC64: 3388020.8 | AD64: -683359.59 | AE64: -47978.87 | AF64: 357576.21 | AG64: 16189.2 | AH64: 2479018 | AI64: -0.72324019 | AJ64: -7.688359 | AK64: 11.10167 | AL64: -3.3460743 | AM64: -11.34444 | AN64: 3.3809188 | AO64: 2.1665082 | AP64: 3.117853
A65: 04518 | C65: JC Stendal | D65: gE | E65: IIId | F65: 15 | G65: Sachsen-Anhalt | K65: 12593839 | L65: 8573220.2 | M65: 42595315 | N65: 24248634 | O65: 384775.43 | P65: 13085187 | Q65: 1186070.5 | R65: 1.0148097e+08 | S65: 12342055 | T65: 9189846.3 | U65: 38359353 | V65: 24950570 | W65: 414389.4 | X65: 12752018 | Y65: 1111117.6 | Z65: 98008233 | AA65: 251783.78 | AB65: -616626.08 | AC65: 4235961.9 | AD65: -701936.17 | AE65: -29613.97 | AF65: 333168.23 | AG65: 74952.81 | AH65: 3472737.7 | AI65: 2.0400475 | AJ65: -6.7098628 | AK65: 11.04284 | AL65: -2.8133071 | AM65: -7.1464111 | AN65: 2.6126705 | AO65: 6.7457133 | AP65: 3.5433123
A66: 04546 | C66: JC Altmarkkreis Salzwedel | D66: zkT | E66: IIIa | F66: 15 | G66: Sachsen-Anhalt | K66: 7737299 | L66: 2414075 | M66: 23145681 | N66: 12006708 | O66: 192869 | P66: 7169633 | Q66: 621443 | R66: 52666265 | S66: 7675564 | T66: 2870415 | U66: 20478316 | V66: 11731905 | W66: 163650 | X66: 6770014 | Y66: 566403 | Z66: 49689864 | AA66: 61735 | AB66: -456340 | AC66: 2667365 | AD66: 274803 | AE66: 29219 | AF66: 399619 | AG66: 55040 | AH66: 2976401 | AI66: 0.80430572 | AJ66: -15.89805 | AK66: 13.025314 | AL66: 2.3423562 | AM66: 17.854568 | AN66: 5.9027795 | AO66: 9.7174627 | AP66: 5.989956
A67: 07146 | C67: JC Erzgebirgskreis | D67: zkT | E67: IIIa | F67: 14 | G67: Sachsen | K67: 19740964 | L67: 5173064 | M67: 55656641 | N67: 32726431 | O67: 1080002 | P67: 17880399 | Q67: 1604087 | R67: 132257501 | S67: 19659489 | T67: 5378441 | U67: 48440553 | V67: 31227223 | W67: 985802 | X67: 16663090 | Y67: 1442138 | Z67: 122354598 | AA67: 81475 | AB67: -205377 | AC67: 7216088 | AD67: 1499208 | AE67: 94200 | AF67: 1217309 | AG67: 161949 | AH67: 9902903 | AI67: 0.41443091 | AJ67: -3.8185229 | AK67: 14.896791 | AL67: 4.8009649 | AM67: 9.5556714 | AN67: 7.3054217 | AO67: 11.229785 | AP67: 8.0936092
A68: 07202 | C68: JC Bautzen | D68: zkT | E68: IIId | F68: 14 | G68: Sachsen | K68: 21227204 | L68: 7637132 | M68: 59309924 | N68: 34743409 | O68: 778762 | P68: 16574692 | Q68: 2319766 | R68: 140271123 | S68: 21034947 | T68: 7028485 | U68: 52768250 | V68: 33923096 | W68: 983286 | X68: 15860420 | Y68: 1819292 | Z68: 131598484 | AA68: 192257 | AB68: 608647 | AC68: 6541674 | AD68: 820313 | AE68: -204524 | AF68: 714272 | AG68: 500474 | AH68: 8672639 | AI68: 0.91398852 | AJ68: 8.6597183 | AK68: 12.396989 | AL68: 2.4181549 | AM68: -20.800052 | AN68: 4.5034873 | AO68: 27.509273 | AP68: 6.5902271
... A88: 09418 | C88: JC Altenburger Land | D88: gE | E88: IIId | F88: 16 | G88: Thüringen | K88: 8917089.3 | L88: 4457238.7 | M88: 31693720 | N88: 18149326 | O88: 645168.08 | P88: 9866337.9 | Q88: 1126681.8 | R88: 73728880 | S88: 8190239.2 | T88: 4525182.5 | U88: 26706562 | V88: 15939901 | W88: 684797 | X88: 8656612.5 | Y88: 725274.69 | Z88: 64703294 | AA88: 726850.12 | AB88: -67943.82 | AC88: 4987158 | AD88: 2209425.5 | AE88: -39628.92 | AF88: 1209725.4 | AG88: 401407.13 | AH88: 9025586.2 | AI88: 8.8745897 | AJ88: -1.5014603 | AK88: 18.673905 | AL88: 13.860974 | AM88: -5.7869588 | AN88: 13.974582 | AO88: 55.345531 | AP88: 13.949191
A89: 09437 | C89: JC Jena, Stadt | D89: zkT | E89: IIIe | F89: 16 | G89: Thüringen | K89: 8761034 | L89: 3803551 | M89: 22965804 | N89: 16157031 | O89: 337261 | P89: 7864565 | Q89: 508083 | R89: 59889246 | S89: . | T89: 3666276 | U89: 20705259 | V89: 15218510 | W89: 502093 | X89: 7325055 | Y89: 460370 | Z89: . | AA89: X | AB89: 137275 | AC89: 2260545 | AD89: 938521 | AE89: -164832 | AF89: 539510 | AG89: 47713 | AH89: X | AI89: X | AJ89: 3.7442626 | AK89: 10.917734 | AL89: 6.1669704 | AM89: -32.828978 | AN89: 7.3652689 | AO89: 10.364055 | AP89: X
A90: 09439 | C90: JC Saale-Holzland-Kreis | D90: gE | E90: IIIa | F90: 16 | G90: Thüringen | K90: 5098789.5 | L90: 1260928 | M90: 12863812 | N90: 7471796.3 | O90: 116165.02 | P90: 4276083.8 | Q90: 391703.35 | R90: 31087574 | S90: 4743826.2 | T90: 1852935 | U90: 11881728 | V90: 7823073.2 | W90: 100543.41 | X90: 4117043.9 | Y90: 350564.78 | Z90: 30519150 | AA90: 354963.32 | AB90: -592006.98 | AC90: 982083.49 | AD90: -351276.94 | AE90: 15621.61 | AF90: 159039.88 | AG90: 41138.57 | AH90: 568424.38 | AI90: 7.4826376 | AJ90: -31.94969 | AK90: 8.2654937 | AL90: -4.4902678 | AM90: 15.537179 | AN90: 3.862963 | AO90: 11.734941 | AP90: 1.8625171
A91: 09441 | C91: JC Saalfeld-Rudolstadt | D91: gE | E91: IIIa | F91: 16 | G91: Thüringen | K91: 7667995.5 | L91: 2980832.5 | M91: 23937002 | N91: 14694241 | O91: 268735.1 | P91: 7600403.5 | Q91: 287856.01 | R91: 57149210 | S91: 7418990.6 | T91: 2543088.8 | U91: 21224646 | V91: 13743814 | W91: 334632.01 | X91: 7072960.9 | Y91: 257122.09 | Z91: 52338132 | AA91: 249004.96 | AB91: 437743.69 | AC91: 2712355.9 | AD91: 950427.13 | AE91: -65896.91 | AF91: 527442.51 | AG91: 30733.92 | AH91: 4811077.3 | AI91: 3.3563186 | AJ91: 17.213071 | AK91: 12.779275 | AL91: 6.9153084 | AM91: -19.692351 | AN91: 7.457167 | AO91: 11.953045 | AP91: 9.1922984
A92: 09446 | C92: JC Greiz | D92: zkT | E92: IIIa | F92: 16 | G92: Thüringen | K92: 5616793 | L92: 2131622 | M92: 17252131 | N92: 9588381 | O92: 253849 | P92: 5467159 | Q92: 524128 | R92: 40309935 | S92: 5542142 | T92: 1797989 | U92: 15057677 | V92: 8954384 | W92: 390347 | X92: 5085407 | Y92: 471760 | Z92: 36827946 | AA92: 74651 | AB92: 333633 | AC92: 2194454 | AD92: 633997 | AE92: -136498 | AF92: 381752 | AG92: 52368 | AH92: 3481989 | AI92: 1.3469702 | AJ92: 18.555898 | AK92: 14.573656 | AL92: 7.0802972 | AM92: -34.968374 | AN92: 7.5068131 | AO92: 11.10056 | AP92: 9.4547467
A93: 09702 | C93: JC Nordhausen | D93: gE | E93: IIId | F93: 16 | G93: Thüringen | K93: 8842670.5 | L93: 3373429.8 | M93: 26688125 | N93: 14471018 | O93: 137400.2 | P93: 8558523.2 | Q93: 1173934.7 | R93: 62071168 | S93: 8609722.8 | T93: 3449755.8 | U93: 23354714 | V93: 14186346 | W93: 269178.1 | X93: 8085413.2 | Y93: 1160712.6 | Z93: 57955130 | AA93: 232947.78 | AB93: -76325.96 | AC93: 3333411.4 | AD93: 284672.4 | AE93: -131777.9 | AF93: 473110.06 | AG93: 13222.09 | AH93: 4116037.8 | AI93: 2.7056363 | AJ93: -2.2125033 | AK93: 14.27297 | AL93: 2.0066647 | AM93: -48.955654 | AN93: 5.8514024 | AO93: 1.1391356 | AP93: 7.1021113
A94: 09704 | C94: JC Eichsfeld | D94: zkT | E94: Ie | F94: 16 | G94: Thüringen | H94: ⁵ | I94: Gemeindeverschiebung | J94: 45292 | K94: 4159387 | L94: 1932046 | M94: 14705121 | N94: 8819166 | O94: 101518 | P94: 4881591 | Q94: 555086 | R94: 34598829 | S94: 4044240 | T94: 2129175 | U94: 13232077 | V94: 8254026 | W94: 200290 | X94: 4604280 | Y94: 462062 | Z94: 32464088 | AA94: 115147 | AB94: -197129 | AC94: 1473044 | AD94: 565140 | AE94: -98772 | AF94: 277311 | AG94: 93024 | AH94: 2134741 | AI94: 2.8471851 | AJ94: -9.2584687 | AK94: 11.132372 | AL94: 6.8468406 | AM94: -49.314494 | AN94: 6.0228961 | AO94: 20.132363 | AP94: 6.5756999
A95: 09708 | C95: JC Kyffhäuserkreis | D95: gE | E95: IIId | F95: 16 | G95: Thüringen | K95: 8165490.1 | L95: 3158723.4 | M95: 22503490 | N95: 12441422 | O95: 436059.76 | P95: 7188208.4 | Q95: 170859.35 | R95: 53893393 | S95: 7902227.2 | T95: 3392879 | U95: 20447632 | V95: 12399169 | W95: 373355.59 | X95: 6979120.8 | Y95: 150981.51 | Z95: 51494383 | AA95: 263262.94 | AB95: -234155.56 | AC95: 2055858.2 | AD95: 42253.27 | AE95: 62704.17 | AF95: 209087.6 | AG95: 19877.84 | AH95: 2399010.6 | AI95: 3.331503 | AJ95: -6.9013826 | AK95: 10.054261 | AL95: 0.34077502 | AM95: 16.794759 | AN95: 2.9959017 | AO95: 13.165745 | AP95: 4.6587812
A96: 09740 | C96: JC Unstrut-Hainich-Kreis | D96: gE | E96: IIId | F96: 16 | G96: Thüringen | H96: ⁵ | I96: Gemeindeverschiebung | J96: 45292 | K96: 9180937.7 | L96: 3586545.3 | M96: 26559007 | N96: 15597214 | O96: 332113.11 | P96: 8753271.6 | Q96: 1083353.6 | R96: 64009089 | S96: 8612582.1 | T96: 4273960.2 | U96: 24230344 | V96: 15309567 | W96: 436847.11 | X96: 8388483.2 | Y96: 725061.12 | Z96: 61251784 | AA96: 568355.51 | AB96: -687414.9 | AC96: 2328662.8 | AD96: 287646.83 | AE96: -104734 | AF96: 364788.46 | AG96: 358292.48 | AH96: 2757304.7 | AI96: 6.5991302 | AJ96: -16.083793 | AK96: 9.610523 | AL96: 1.8788698 | AM96: -23.974978 | AN96: 4.348682 | AO96: 49.415487 | AP96: 4.5015909
A97: 09802 | C97: JC Suhl, Stadt | D97: gE | E97: IIIa | F97: 16 | G97: Thüringen | K97: 2533372.6 | L97: 1023343.4 | M97: 7422086 | N97: 4266541.7 | O97: 84195.28 | P97: 2365370.4 | Q97: 231862.54 | R97: 17694909 | S97: 2409948 | T97: 1020895.1 | U97: 6383040.8 | V97: 4099952.8 | W97: 123160.12 | X97: 2232545.4 | Y97: 227517.81 | Z97: 16269542 | AA97: 123424.6 | AB97: 2448.33 | AC97: 1039045.3 | AD97: 166588.85 | AE97: -38964.84 | AF97: 132824.93 | AG97: 4344.73 | AH97: 1425367.2 | AI97: 5.1214632 | AJ97: 0.2398219 | AK97: 16.278218 | AL97: 4.0631894 | AM97: -31.637546 | AN97: 5.9494839 | AO97: 1.9096219 | AP97: 8.7609542
A98: 09804 | C98: JC Hildburghausen | D98: gE | E98: Ie | F98: 16 | G98: Thüringen | K98: 2831644.1 | L98: 794465.1 | M98: 8120321.1 | N98: 4178831.4 | O98: 60792.4 | P98: 2615574.3 | Q98: 162757.18 | R98: 18601628 | S98: 2745854 | T98: 609218.72 | U98: 7398708.7 | V98: 4251506.3 | W98: 138445.56 | X98: 2516874.6 | Y98: 145915.15 | Z98: 17660608 | AA98: 85790.03 | AB98: 185246.38 | AC98: 721612.39 | AD98: -72674.86 | AE98: -77653.16 | AF98: 98699.65 | AG98: 16842.03 | AH98: 941020.43 | AI98: 3.1243478 | AJ98: 30.407204 | AK98: 9.7532207 | AL98: -1.7093909 | AM98: -56.08931 | AN98: 3.9215163 | AO98: 11.542345 | AP98: 5.3283581
A99: 09806 | C99: JC Sonneberg | D99: gE | E99: Ie | F99: 16 | G99: Thüringen | K99: 3139757.7 | L99: 939409.61 | M99: 8185053.4 | N99: 4842546.4 | O99: 68673.31 | P99: 2725348 | Q99: 0 | R99: 19900788 | S99: 2962490.2 | T99: 767672.34 | U99: 7576234.1 | V99: 4435302.4 | W99: 63283.45 | X99: 2662814 | Y99: 220549 | Z99: 18467797 | AA99: 177267.48 | AB99: 171737.27 | AC99: 608819.33 | AD99: 407244.05 | AE99: 5389.86 | AF99: 62533.95 | AG99: -220549 | AH99: 1432991.9 | AI99: 5.9837321 | AJ99: 22.371168 | AK99: 8.0359097 | AL99: 9.181878 | AM99: 8.5170135 | AN99: 2.348416 | AO99: -100 | AP99: 7.7594094
A100: 09810 | C100: JC Wartburgkreis | D100: gE | E100: Ie | F100: 16 | G100: Thüringen | H100: ⁵ | I100: Gemeindeverschiebung | J100: 45292 | K100: 11103476 | L100: 3303039.3 | M100: 30452268 | N100: 17758678 | O100: 555205.62 | P100: 9577551.2 | Q100: 994687.44 | R100: 72750219 | S100: 11031561 | T100: 3494491.6 | U100: 27474897 | V100: 18242937 | W100: 752162.48 | X100: 9229137.9 | Y100: 899616.6 | Z100: 70225188 | AA100: 71914.91 | AB100: -191452.24 | AC100: 2977371.1 | AD100: -484259.01 | AE100: -196956.86 | AF100: 348413.21 | AG100: 95070.84 | AH100: 2525031.1 | AI100: 0.65190147 | AJ100: -5.4786866 | AK100: 10.836696 | AL100: -2.6545013 | AM100: -26.185414 | AN100: 3.7751436 | AO100: 10.567929 | AP100: 3.5956203
A101: 09840 | C101: JC Schmalkalden-Meiningen | D101: zkT | E101: Ie | F101: 16 | G101: Thüringen | K101: 5432978 | L101: 1764583 | M101: 18118705 | N101: 10844726 | O101: 210844 | P101: 5600239 | Q101: 505100 | R101: 41972075 | S101: 5639492 | T101: 2067908 | U101: 16785033 | V101: 10706298 | W101: 210376 | X101: 5337860 | Y101: 472953 | Z101: 40746967 | AA101: -206514 | AB101: -303325 | AC101: 1333672 | AD101: 138428 | AE101: 468 | AF101: 262379 | AG101: 32147 | AH101: 1225108 | AI101: -3.6619256 | AJ101: -14.668206 | AK101: 7.9456025 | AL101: 1.2929586 | AM101: 0.22245884 | AN101: 4.9154343 | AO101: 6.7970813 | AP101: 3.0066238
A102: 11102 | C102: JC Stormarn | D102: gE | E102: IIc | F102: 01 | G102: Schleswig-Holstein | K102: 12092903 | L102: 7050917 | M102: 44981653 | N102: 40126560 | O102: 679153.45 | P102: 15144983 | Q102: 2182778.2 | R102: 1.2007617e+08 | S102: 11036626 | T102: 6548394.9 | U102: 36654198 | V102: 36202271 | W102: 748232.1 | X102: 13704607 | Y102: 1878230.3 | Z102: 1.0489433e+08 | AA102: 1056277.5 | AB102: 502522.14 | AC102: 8327455.9 | AD102: 3924289.5 | AE102: -69078.65 | AF102: 1440376.6 | AG102: 304547.85 | AH102: 15181843 | AI102: 9.5706559 | AJ102: 7.6739743 | AK102: 22.718969 | AL102: 10.839899 | AM102: -9.2322489 | AN102: 10.510164 | AO102: 16.214617 | AP102: 14.473464
A103: 11116 | C103: JC Herzogtum Lauenburg | D103: gE | E103: IIc | F103: 01 | G103: Schleswig-Holstein | K103: 13153103 | L103: 8040078.9 | M103: 47459394 | N103: 38291631 | O103: 389660.59 | P103: 15790558 | Q103: 1348786.4 | R103: 1.2312442e+08 | S103: 12226204 | T103: 6984405.9 | U103: 41061625 | V103: 35930132 | W103: 511002.7 | X103: 14527945 | Y103: 1263638.2 | Z103: 1.1124132e+08 | AA103: 926898.33 | AB103: 1055673 | AC103: 6397768.6 | AD103: 2361498.7 | AE103: -121342.11 | AF103: 1262612.6 | AG103: 85148.2 | AH103: 11883109 | AI103: 7.5812436 | AJ103: 15.114714 | AK103: 15.580895 | AL103: 6.5724744 | AM103: -23.745884 | AN103: 8.6909231 | AO103: 6.7383371 | AP103: 10.68228
A104: 11502 | C104: JC Pinneberg | D104: gE | E104: IIc | F104: 01 | G104: Schleswig-Holstein | K104: 23983039 | L104: 11114294 | M104: 83218574 | N104: 78385518 | O104: 791435.21 | P104: 27998932 | Q104: 1211958 | R104: 2.2549179e+08 | S104: 22540364 | T104: 13743804 | U104: 70925576 | V104: 72516531 | W104: 930846.29 | X104: 25992996 | Y104: 1257584 | Z104: 2.0665012e+08 | AA104: 1442675.2 | AB104: -2629509.7 | AC104: 12292997 | AD104: 5868987.3 | AE104: -139411.08 | AF104: 2005935.7 | AG104: -45626 | AH104: 18841674 | AI104: 6.4004077 | AJ104: -19.132329 | AK104: 17.332249 | AL104: 8.0933095 | AM104: -14.97681 | AN104: 7.7172163 | AO104: -3.6280678 | AP104: 9.1176694
A105: 11522 | C105: JC Segeberg | D105: gE | E105: IIc | F105: 01 | G105: Schleswig-Holstein | K105: 16893287 | L105: 8204418.2 | M105: 59084614 | N105: 52459227 | O105: 489409.28 | P105: 19894660 | Q105: 2083612.5 | R105: 1.5702562e+08 | S105: 15372606 | T105: 8443329.1 | U105: 49392118 | V105: 48304860 | W105: 530734.11 | X105: 17875923 | Y105: 1761931 | Z105: 1.3991957e+08 | AA105: 1520681 | AB105: -238910.87 | AC105: 9692496.1 | AD105: 4154367.5 | AE105: -41324.83 | AF105: 2018737.1 | AG105: 321681.45 | AH105: 17106046 | AI105: 9.8921481 | AJ105: -2.8295814 | AK105: 19.623568 | AL105: 8.6003096 | AM105: -7.7863528 | AN105: 11.293051 | AO105: 18.257324 | AP105: 12.225628
A106: 11902 | C106: JC Flensburg, Stadt | D106: gE | E106: IIIb | F106: 01 | G106: Schleswig-Holstein | K106: 14630252 | L106: 5608882.7 | M106: 38787283 | N106: 29587803 | O106: 521753.75 | P106: 12863404 | Q106: 1560075.8 | R106: 1.0199938e+08 | S106: 13773616 | T106: 8311663.6 | U106: 34039542 | V106: 28561763 | W106: 639173.6 | X106: 12391025 | Y106: 1561855.6 | Z106: 97716784 | AA106: 856635.39 | AB106: -2702780.9 | AC106: 4747740.9 | AD106: 1026039.5 | AE106: -117419.85 | AF106: 472379.4 | AG106: -1779.77 | AH106: 4282594.5 | AI106: 6.2193935 | AJ106: -32.517929 | AK106: 13.947723 | AL106: 3.5923537 | AM106: -18.370573 | AN106: 3.8122707 | AO106: -0.11395228 | AP106: 4.3826601
A107: 11904 | C107: JC Schleswig-Flensburg | D107: zkT | E107: IIc | F107: 01 | G107: Schleswig-Holstein | K107: 13213863 | L107: 5059856 | M107: 41054376 | N107: 31473727 | O107: 412523 | P107: 13327334 | Q107: 2470203 | R107: 104541679 | S107: 12985008 | T107: 6130861 | U107: 34473175 | V107: 30884123 | W107: 437536 | X107: 12861138 | Y107: 1173003 | Z107: 97771841 | AA107: 228855 | AB107: -1071005 | AC107: 6581201 | AD107: 589604 | AE107: -25013 | AF107: 466196 | AG107: 1297200 | AH107: 6769838 | AI107: 1.7624556 | AJ107: -17.46908 | AK107: 19.090789 | AL107: 1.9090845 | AM107: -5.7167867 | AN107: 3.6248425 | AO107: 110.58795 | AP107: 6.9241184
A108: 11916 | C108: JC Nordfriesland | D108: zkT | E108: IIc | F108: 01 | G108: Schleswig-Holstein | K108: 11117751 | L108: 3973422 | M108: 33473996 | N108: 27741323 | O108: 200658 | P108: 11033513 | Q108: 1389138 | R108: 87540663 | S108: 10405749 | T108: 3886734 | U108: 27471610 | V108: 25976224 | W108: 167501 | X108: 10198953 | Y108: 1124689 | Z108: 78106771 | AA108: 712002 | AB108: 86688 | AC108: 6002386 | AD108: 1765099 | AE108: 33157 | AF108: 834560 | AG108: 264449 | AH108: 9433892 | AI108: 6.8423907 | AJ108: 2.2303559 | AK108: 21.849415 | AL108: 6.7950561 | AM108: 19.795106 | AN108: 8.1828007 | AO108: 23.513078 | AP108: 12.0782
A109: 12302 | C109: JC Hamburg, Freie und Hansestadt | D109: gE | E109: IIIb | F109: 02 | G109: Hamburg | K109: 1.9823893e+08 | L109: 1.5194415e+08 | M109: 7.6029108e+08 | N109: 8.5394905e+08 | O109: 8170745.2 | P109: 2.4685997e+08 | Q109: 44568283 | R109: 2.2194539e+09 | S109: 1.8463347e+08 | T109: 1.7592508e+08 | U109: 6.5927862e+08 | V109: 757451424 | W109: 9924418.2 | X109: 2.3275562e+08 | Y109: 39604371 | Z109: 2.0199686e+09 | AA109: 13605467 | AB109: -23980938 | AC109: 1.0101246e+08 | AD109: 96497622 | AE109: -1753673.1 | AF109: 14104357 | AG109: 4963911.9 | AH109: 1.9948529e+08 | AI109: 7.3689063 | AJ109: -13.631335 | AK109: 15.321664 | AL109: 12.739777 | AM109: -17.670286 | AN109: 6.059728 | AO109: 12.533748 | AP109: 9.8756629
A110: 12702 | C110: JC Dithmarschen | D110: gE | E110: IIc | F110: 01 | G110: Schleswig-Holstein | K110: 11180909 | L110: 6226741.8 | M110: 37034034 | N110: 27138695 | O110: 380259.72 | P110: 12182696 | Q110: 1026504.8 | R110: 94143335 | S110: 10642223 | T110: 6892147.2 | U110: 32000942 | V110: 25503368 | W110: 437006.3 | X110: 11306529 | Y110: 996079.29 | Z110: 86782215 | AA110: 538685.64 | AB110: -665405.41 | AC110: 5033092.5 | AD110: 1635326.9 | AE110: -56746.58 | AF110: 876167.15 | AG110: 30425.52 | AH110: 7361120.2 | AI110: 5.0617772 | AJ110: -9.6545444 | AK110: 15.727951 | AL110: 6.4121998 | AM110: -12.9853 | AN110: 7.7492144 | AO110: 3.0545279 | AP110: 8.4822912
A111: 12712 | C111: JC Steinburg | D111: gE | E111: IIc | F111: 01 | G111: Schleswig-Holstein | K111: 10663540 | L111: 4980100.9 | M111: 33560682 | N111: 23974599 | O111: 136003.66 | P111: 11047868 | Q111: 855286.39 | R111: 84362794 | S111: 10156225 | T111: 5734328.4 | U111: 29033642 | V111: 22783831 | W111: 177446.61 | X111: 10230900 | Y111: 755977.4 | Z111: 78116373 | AA111: 507315.19 | AB111: -754227.46 | AC111: 4527040 | AD111: 1190767.8 | AE111: -41442.95 | AF111: 816968.04 | AG111: 99308.99 | AH111: 6246420.6 | AI111: 4.9951157 | AJ111: -13.152847 | AK111: 15.592395 | AL111: 5.2263721 | AM111: -23.355166 | AN111: 7.9852996 | AO111: 13.136502 | AP111: 7.9963014
A112: 13102 | C112: JC Kiel, Landeshauptstadt | D112: gE | E112: IIIb | F112: 01 | G112: Schleswig-Holstein | K112: 33621851 | L112: 22874671 | M112: 1.0908613e+08 | N112: 86667842 | O112: 1539419.6 | P112: 36827552 | Q112: 1784031 | R112: 2.9061746e+08 | S112: 33332105 | T112: 26732628 | U112: 96739478 | V112: 82591130 | W112: 1256025.9 | X112: 35185924 | Y112: 1759261.3 | Z112: 2.7583729e+08 | AA112: 289745.66 | AB112: -3857956.4 | AC112: 12346650 | AD112: 4076711.2 | AE112: 283393.7 | AF112: 1641628 | AG112: 24769.72 | AH112: 14780172 | AI112: 0.86926901 | AJ112: -14.431639 | AK112: 12.762784 | AL112: 4.9360157 | AM112: 22.562727 | AN112: 4.6655817 | AO112: 1.4079614 | AP112: 5.3582937
... A122: 21404 | C122: JC Bremen, Stadt | D122: gE | E122: IIIb | F122: 04 | G122: Bremen | K122: 80605397 | L122: 64825102 | M122: 3.056285e+08 | N122: 2.4726915e+08 | O122: 3924501.2 | P122: 96913895 | Q122: 3411164.2 | R122: 7.9916654e+08 | S122: 79859190 | T122: 69602685 | U122: 2.6448271e+08 | V122: 2.3651634e+08 | W122: 4169275.3 | X122: 90857867 | Y122: 3254360.8 | Z122: 7.4548807e+08 | AA122: 746206.76 | AB122: -4777582.8 | AC122: 41145790 | AD122: 10752801 | AE122: -244774.06 | AF122: 6056028.2 | AG122: 156803.37 | AH122: 53678468 | AI122: 0.93440312 | AJ122: -6.8640784 | AK122: 15.557081 | AL122: 4.5463245 | AM122: -5.8709019 | AN122: 6.6653867 | AO122: 4.818254 | AP122: 7.2004463
A123: 21416 | C123: JC Osterholz | D123: zkT | E123: IIc | F123: 03 | G123: Niedersachsen | K123: 5535100 | L123: 1485559 | M123: . | N123: 13384180 | O123: 79262 | P123: 5458425 | Q123: 546277 | R123: . | S123: 5971023 | T123: 1843750 | U123: 16760496 | V123: 13115555 | W123: 129248 | X123: 5289925 | Y123: 508325 | Z123: 43109997 | AA123: -435923 | AB123: -358191 | AC123: X | AD123: 268625 | AE123: -49986 | AF123: 168500 | AG123: 37952 | AH123: X | AI123: -7.3006418 | AJ123: -19.427308 | AK123: X | AL123: 2.0481405 | AM123: -38.674486 | AN123: 3.1853004 | AO123: 7.4660896 | AP123: X
A124: 21420 | C124: JC Bremerhaven, Stadt | D124: gE | E124: IIIc | F124: 04 | G124: Bremen | K124: 22627201 | L124: 16095704 | M124: 81119365 | N124: 55734391 | O124: 1436029.4 | P124: 25579095 | Q124: 2765337.1 | R124: 2.0259179e+08 | S124: 21712296 | T124: 16916763 | U124: 69166250 | V124: 53379863 | W124: 1382185.5 | X124: 23983866 | Y124: 2439484.5 | Z124: 1.8654122e+08 | AA124: 914905.38 | AB124: -821058.52 | AC124: 11953115 | AD124: 2354528.8 | AE124: 53843.89 | AF124: 1595229.2 | AG124: 325852.61 | AH124: 16050564 | AI124: 4.2137662 | AJ124: -4.8535203 | AK124: 17.281716 | AL124: 4.4108933 | AM124: 3.8955617 | AN124: 6.6512594 | AO124: 13.357437 | AP124: 8.6042985
A125: 22102 | C125: JC Celle | D125: gE | E125: IId | F125: 03 | G125: Niedersachsen | K125: 15902109 | L125: 6755773 | M125: 48502088 | N125: 35342677 | O125: 365596.02 | P125: 16017242 | Q125: 1663626.9 | R125: 1.2288549e+08 | S125: 15544934 | T125: 7562352.1 | U125: 44202068 | V125: 34838491 | W125: 545963.64 | X125: 15579420 | Y125: 1533613.8 | Z125: 1.1827323e+08 | AA125: 357175.76 | AB125: -806579.1 | AC125: 4300020.8 | AD125: 504186.11 | AE125: -180367.62 | AF125: 437822.11 | AG125: 130013.07 | AH125: 4612258.1 | AI125: 2.2976988 | AJ125: -10.665717 | AK125: 9.7280988 | AL125: 1.44721 | AM125: -33.036563 | AN125: 2.8102594 | AO125: 8.4775623 | AP125: 3.8996637
A126: 22116 | C126: JC Heidekreis | D126: zkT | E126: IIc | F126: 03 | G126: Niedersachsen | K126: 9414896 | L126: 6598112 | M126: 34457867 | N126: 25716303 | O126: 244384 | P126: 11335110 | Q126: 1077106 | R126: 87766672 | S126: 9000000 | T126: 6918138 | U126: 29982619 | V126: 24586772 | W126: 290126 | X126: 10603118 | Y126: 981308 | Z126: 81380773 | AA126: 414896 | AB126: -320026 | AC126: 4475248 | AD126: 1129531 | AE126: -45742 | AF126: 731992 | AG126: 95798 | AH126: 6385899 | AI126: 4.6099556 | AJ126: -4.6258979 | AK126: 14.926141 | AL126: 4.5940598 | AM126: -15.766253 | AN126: 6.9035542 | AO126: 9.7622765 | AP126: 7.8469382
A127: 22402 | C127: JC Emden, Stadt | D127: gE | E127: IIIb | F127: 03 | G127: Niedersachsen | K127: 6490566.9 | L127: 3432896.9 | M127: 20406537 | N127: 14677061 | O127: 189061.15 | P127: 6535856.7 | Q127: 426849.87 | R127: 51731980 | S127: 6132586.4 | T127: 3663248 | U127: 17768490 | V127: 13953593 | W127: 247772.94 | X127: 6216373.2 | Y127: 347928.51 | Z127: 47982064 | AA127: 357980.51 | AB127: -230351.08 | AC127: 2638046.9 | AD127: 723467.55 | AE127: -58711.79 | AF127: 319483.57 | AG127: 78921.36 | AH127: 3749915.6 | AI127: 5.8373496 | AJ127: -6.2881651 | AK127: 14.84677 | AL127: 5.1848118 | AM127: -23.695804 | AN127: 5.1393885 | AO127: 22.683212 | AP127: 7.8152445
A128: 22410 | C128: JC Leer | D128: zkT | E128: IIc | F128: 03 | G128: Niedersachsen | K128: 11183527 | L128: 6498718 | M128: . | N128: 26332039 | O128: 240260 | P128: 12317338 | Q128: 1383711 | R128: . | S128: 11122572 | T128: 5897015 | U128: 32575828 | V128: 25848391 | W128: 432760 | X128: 11690121 | Y128: 1333726 | Z128: 87566687 | AA128: 60955 | AB128: 601703 | AC128: X | AD128: 483648 | AE128: -192500 | AF128: 627217 | AG128: 49985 | AH128: X | AI128: 0.54802972 | AJ128: 10.203518 | AK128: X | AL128: 1.8710952 | AM128: -44.48193 | AN128: 5.3653593 | AO128: 3.7477713 | AP128: X
A129: 22444 | C129: JC Wittmund | D129: zkT | E129: IIc | F129: 03 | G129: Niedersachsen | K129: 4771790 | L129: 1371970 | M129: 12193654 | N129: 9549244 | O129: 129133 | P129: 4317971 | Q129: 448580 | R129: 32333762 | S129: 4319695 | T129: 1409363 | U129: 11014162 | V129: 9507269 | W129: 179342 | X129: 4155879 | Y129: 440648 | Z129: 30585710 | AA129: 452095 | AB129: -37393 | AC129: 1179492 | AD129: 41975 | AE129: -50209 | AF129: 162092 | AG129: 7932 | AH129: 1748052 | AI129: 10.465901 | AJ129: -2.6531845 | AK129: 10.708867 | AL129: 0.44150428 | AM129: -27.996231 | AN129: 3.900306 | AO129: 1.8000763 | AP129: 5.7152572
A130: 22446 | C130: JC Aurich | D130: zkT | E130: IIc | F130: 03 | G130: Niedersachsen | K130: 15261061 | L130: 6311629 | M130: 47586488 | N130: 34945568 | O130: 208959 | P130: 14507247 | Q130: 1440443 | R130: 118820952 | S130: 14843857 | T130: 7573393 | U130: 41457227 | V130: 33716542 | W130: 58204 | X130: 14727738 | Y130: 2031552 | Z130: 112376961 | AA130: 417204 | AB130: -1261764 | AC130: 6129261 | AD130: 1229026 | AE130: 150755 | AF130: -220491 | AG130: -591109 | AH130: 6443991 | AI130: 2.8106172 | AJ130: -16.660485 | AK130: 14.784542 | AL130: 3.6451722 | AM130: .X | AN130: -1.4971138 | AO130: -29.096425 | AP130: 5.7342634
A131: 23102 | C131: JC Göttingen | D131: zkT | E131: IId | F131: 03 | G131: Niedersachsen | K131: 28259357 | L131: 11032063 | M131: 83774972 | N131: 64172869 | O131: 894556 | P131: 27305479 | Q131: 4973588 | R131: 215439296 | S131: 26899961 | T131: 10002200 | U131: 71734307 | V131: 61451945 | W131: 1258726 | X131: 25361757 | Y131: 4519167 | Z131: 196708896 | AA131: 1359396 | AB131: 1029863 | AC131: 12040665 | AD131: 2720924 | AE131: -364170 | AF131: 1943722 | AG131: 454421 | AH131: 18730400 | AI131: 5.0535241 | AJ131: 10.296365 | AK131: 16.785086 | AL131: 4.4277264 | AM131: -28.931634 | AN131: 7.6639879 | AO131: 10.055415 | AP131: 9.5218876
A132: 23106 | C132: JC Northeim | D132: gE | E132: IIa | F132: 03 | G132: Niedersachsen | K132: 10520328 | L132: 5091538.4 | M132: 34286711 | N132: 22000479 | O132: 372309.69 | P132: 11146780 | Q132: 407207.6 | R132: 83418146 | S132: 9730046.2 | T132: 5171267.4 | U132: 29785300 | V132: 21007839 | W132: 541061.97 | X132: 10457323 | Y132: 366109.77 | Z132: 76692838 | AA132: 790281.86 | AB132: -79729.04 | AC132: 4501411 | AD132: 992640.53 | AE132: -168752.28 | AF132: 689456.53 | AG132: 41097.83 | AH132: 6725308.6 | AI132: 8.1220771 | AJ132: -1.5417698 | AK132: 15.112861 | AL132: 4.7250959 | AM132: -31.189085 | AN132: 6.59305 | AO132: 11.225549 | AP132: 8.7691483
A133: 23406 | C133: JC Holzminden | D133: gE | E133: IId | F133: 03 | G133: Niedersachsen | K133: 6431540 | L133: 2993976.4 | M133: 20384092 | N133: 12589934 | O133: 273640.84 | P133: 6495103.2 | Q133: 510683.41 | R133: 49168286 | S133: 6141778 | T133: 2993759.7 | U133: 17970644 | V133: 12199899 | W133: 364348.08 | X133: 6173659.6 | Y133: 426693.96 | Z133: 45844088 | AA133: 289761.99 | AB133: 216.7 | AC133: 2413447.6 | AD133: 390035.61 | AE133: -90707.24 | AF133: 321443.64 | AG133: 83989.45 | AH133: 3324198.3 | AI133: 4.7178845 | AJ133: 0.0072383898 | AK133: 13.429945 | AL133: 3.1970398 | AM133: -24.895765 | AN133: 5.2066953 | AO133: 19.683768 | AP133: 7.251095
A134: 23408 | C134: JC Hameln-Pyrmont | D134: gE | E134: IIc | F134: 03 | G134: Niedersachsen | K134: 14522852 | L134: 8425511 | M134: 50425743 | N134: 35897640 | O134: 487811.25 | P134: 16169646 | Q134: 1428886.7 | R134: 1.259292e+08 | S134: 13421627 | T134: 8386795.1 | U134: 43938463 | V134: 34670934 | W134: 686232.75 | X134: 15270893 | Y134: 1368470.3 | Z134: 1.1637495e+08 | AA134: 1101224.9 | AB134: 38715.83 | AC134: 6487279.9 | AD134: 1226705.5 | AE134: -198421.5 | AF134: 898753.18 | AG134: 60416.37 | AH134: 9554257.8 | AI134: 8.204854 | AJ134: 0.46162842 | AK134: 14.764467 | AL134: 3.538138 | AM134: -28.914607 | AN134: 5.8854004 | AO134: 4.4148835 | AP134: 8.2098924
A135: 23444 | C135: JC Schaumburg | D135: zkT | E135: IIc | F135: 03 | G135: Niedersachsen | K135: 11116482 | L135: 5882408 | M135: 36691094 | N135: 26132397 | O135: 319018 | P135: 12097090 | Q135: 2022256 | R135: 92238489 | S135: 10631543 | T135: 6477285 | U135: 31815628 | V135: 25311369 | W135: 368593 | X135: 11523364 | Y135: 1890618 | Z135: 86127782 | AA135: 484939 | AB135: -594877 | AC135: 4875466 | AD135: 821028 | AE135: -49575 | AF135: 573726 | AG135: 131638 | AH135: 6110707 | AI135: 4.5613228 | AJ135: -9.1840486 | AK135: 15.324123 | AL135: 3.2437123 | AM135: -13.449794 | AN135: 4.9788065 | AO135: 6.9626969 | AP135: 7.0949313
...
